Workbook

Sheet Resumen
A1: Casa Brisa · costo total del proyecto
A2: Barranquilla, precios de octubre de 2026. Celdas amarillas: parámetros editables.
A4: Parámetro | B4: Bajo | C4: Medio | D4: Alto | E4: Fuente
A5: Área construida (m²) | B5: 251.44 | C5: 251.44 | D5: 251.44 | E5: supuesto propio
A6: Diseño arquitectónico (COP/m²) | B6: 45000 | C6: 70000 | D6: 110000 | E6: S2: Diseño arquitectónico completo (anteproyecto, proyecto y pla
A7: Diseño estructural (COP/m²) | B7: 12000 | C7: 18000 | D7: 28000 | E7: S3: Diseño estructural NSR-10
A8: Diseños eléctrico e hidrosanitario (COP) | B8: 5000000 | C8: 8000000 | D8: 12000000 | E8: S4: Diseños eléctrico RETIE, hidrosanitario y de gas
A9: Estudio de suelos (COP) | B9: 3000000 | C9: 4500000 | D9: 7000000 | E9: S1: Estudio de suelos con ensayos de expansión
A10: Levantamiento topográfico (COP) | B10: 1200000 | C10: 1800000 | D10: 2800000 | E10: S7: Levantamiento topográfico
A11: Expensas de curaduría (COP) | B11: 9000000 | C11: 9900000 | D11: 11000000 | E11: S5: Expensas de licencia de construcción en curaduría (251 m², e
A12: AIU (% del costo directo) | B12: 0.18 | C12: 0.25 | D12: 0.3 | E12: B4: AIU total típico de contratista a precio global en vivienda
A13: Interventoría (% del costo directo) | B13: 0.03 | C13: 0.04 | D13: 0.06 | E13: S6: Interventoría o supervisión técnica
A14: Delineación urbana (% de la obra) | B14: 0.03 | C14: 0.03 | D14: 0.03 | E14: B6: Tarifa del impuesto de delineación urbana en Barranquilla
A15: Base mínima de delineación (COP/m²) | B15: 2019139 | C15: 2019139 | D15: 2019139 | E15: B7: Costo mínimo por m², uso residencial estrato 6, unifamiliar-
A16: Utilidad dentro del AIU | B16: 0.3 | C16: 0.3 | D16: 0.3 | E16: supuesto propio
... A18: Pólizas (% del contrato) | B18: 0.006 | C18: 0.009 | D18: 0.013 | E18: S8: Pólizas de cumplimiento y responsabilidad civil
A20: Concepto | B20: Bajo | C20: Medio | D20: Alto | E20: Cómo se calcula
A21: Costo directo de obra | B21: =Partidas!K87 | C21: =Partidas!L87 | D21: =Partidas!M87 | E21: suma de las partidas
A22: Diseño arquitectónico | B22: =B6*B5 | C22: =C6*C5 | D22: =D6*D5 | E22: S2 × área
A23: Diseño estructural NSR-10 | B23: =B7*B5 | C23: =C7*C5 | D23: =D7*D5 | E23: S3 × área
A24: Diseños eléctrico RETIE e hidrosanitario | B24: =B8 | C24: =C8 | D24: =D8 | E24: S4
A25: Estudio de suelos | B25: =B9 | C25: =C9 | D25: =D9 | E25: S1
A26: Levantamiento topográfico | B26: =B10 | C26: =C10 | D26: =D10 | E26: S7
A27: Expensas de licencia (curaduría) | B27: =B11 | C27: =C11 | D27: =D11 | E27: S5
A28: Impuesto de delineación urbana | B28: =B14*MAX(B21*(1+B12),B15*B5) | C28: =C14*MAX(C21*(1+C12),C15*C5) | D28: =D14*MAX(D21*(1+D12),D15*D5) | E28: B6 × mayor entre obra con AIU y B7 × área
A29: Interventoría | B29: =B13*B21 | C29: =C13*C21 | D29: =D13*D21 | E29: S6 × costo directo
A30: AIU del constructor | B30: =B12*B21 | C30: =C12*C21 | D30: =D12*D21 | E30: B4 × costo directo
A31: IVA sobre la utilidad | B31: =B17*B16*B12*B21 | C31: =C17*C16*C12*C21 | D31: =D17*D16*D12*D21 | E31: B8 × utilidad (30 % del AIU)
A32: Pólizas | B32: =B18*B21*(1+B12) | C32: =C18*C21*(1+C12) | D32: =D18*D21*(1+D12) | E32: S8 × valor del contrato
A33: Total del proyecto | B33: =SUM(B21:B32) | C33: =SUM(C21:C32) | D33: =SUM(D21:D32)
A34: Total por m² construido | B34: =B33/B5 | C34: =C33/C5 | D34: =D33/D5
A35: Mano de obra (% del costo directo) | B35: =Partidas!N87/Partidas!K87 | C35: =Partidas!O87/Partidas!L87 | D35: =Partidas!P87/Partidas!M87
A37: Valores de referencia calculados por presupuesto.py (deben coincidir sin cambios): | B37: 1562249374 | C37: 2300133658 | D37: 3450062579

Sheet Partidas
A1: Presupuesto de obra de Casa Brisa · costo directo por partida (COP, octubre de 2026)
A2: Celdas amarillas: cantidades y precios unitarios editables. Totales y mano de obra se calculan.
A4: Capítulo | B4: Partida | C4: Unidad | D4: Cantidad | E4: PU bajo | F4: PU medio | G4: PU alto | H4: % MO bajo | I4: % MO medio | J4: % MO alto | K4: Total bajo | L4: Total medio | M4: Total alto | N4: MO bajo | O4: MO medio | P4: MO alto | Q4: Base del precio | R4: Medición
A5: Preliminares y obra provisional | B5: Cerramiento provisional del lote | C5: ml | D5: 101.4 | E5: 38265 | F5: 51434 | G5: 72740 | H5: 0.5296 | I5: 0.4945 | J5: 0.4776 | K5: =ROUND(D5*E5,0) | L5: =ROUND(D5*F5,0) | M5: =ROUND(D5*G5,0) | N5: =ROUND(K5*H5,0) | O5: =ROUND(L5*I5,0) | P5: =ROUND(M5*J5,0) | Q5: supuesto de material + 0,1 jornal de cuadrilla por ml (L3, L4, L5) | R5: perímetro del lote 24,4 × 26,3 m
A6: Preliminares y obra provisional | B6: Campamento, bodega y baño de obra | C6: mes | D6: 12 | E6: 1100000 | F6: 1500000 | G6: 2100000 | H6: 0.1 | I6: 0.1 | J6: 0.1 | K6: =ROUND(D6*E6,0) | L6: =ROUND(D6*F6,0) | M6: =ROUND(D6*G6,0) | N6: =ROUND(K6*H6,0) | O6: =ROUND(L6*I6,0) | P6: =ROUND(M6*J6,0) | Q6: supuesto de alquiler mensual | R6: duración de obra física del cronograma
A7: Preliminares y obra provisional | B7: Servicios provisionales de agua y energía | C7: mes | D7: 12 | E7: 550000 | F7: 850000 | G7: 1250000 | H7: 0 | I7: 0 | J7: 0 | K7: =ROUND(D7*E7,0) | L7: =ROUND(D7*F7,0) | M7: =ROUND(D7*G7,0) | N7: =ROUND(K7*H7,0) | O7: =ROUND(L7*I7,0) | P7: =ROUND(M7*J7,0) | Q7: supuesto de consumo mensual | R7: duración de obra física del cronograma
A8: Preliminares y obra provisional | B8: Vigilancia nocturna | C8: mes | D8: 12 | E8: 2875452 | F8: 3085561 | G8: 3400724 | H8: 1 | I8: 1 | J8: 1 | K8: =ROUND(D8*E8,0) | L8: =ROUND(D8*F8,0) | M8: =ROUND(D8*G8,0) | N8: =ROUND(K8*H8,0) | O8: =ROUND(L8*I8,0) | P8: =ROUND(M8*J8,0) | Q8: un vigilante con salario mínimo 2026 y factor prestacional (L1, L2, L5) | R8: duración de obra física del cronograma
A9: Preliminares y obra provisional | B9: Localización, replanteo y control topográfico | C9: m² | D9: 251.44 | E9: 2864 | F9: 4295 | G9: 6682 | H9: 0.8 | I9: 0.8 | J9: 0.8 | K9: =ROUND(D9*E9,0) | L9: =ROUND(D9*F9,0) | M9: =ROUND(D9*G9,0) | N9: =ROUND(K9*H9,0) | O9: =ROUND(L9*I9,0) | P9: =ROUND(M9*J9,0) | Q9: 60 % de un levantamiento topográfico (S7) repartido por m² | R9: PB 159.8 + PA 91.64
A10: Movimiento de tierras y cimentación | B10: Excavación mecánica | C10: m³ | D10: 334.67 | E10: 15000 | F10: 26000 | G10: 38000 | H10: 0.15 | I10: 0.15 | J10: 0.15 | K10: =ROUND(D10*E10,0) | L10: =ROUND(D10*F10,0) | M10: =ROUND(D10*G10,0) | N10: =ROUND(K10*H10,0) | O10: =ROUND(L10*I10,0) | P10: =ROUND(M10*J10,0) | Q10: G9 (sin retiro) | R10: mejoramiento 0,6 m bajo huella+10 m² + 26 zapatas 1,6×1,6×0,9 + vaso de piscina y canal + zanja del muro de contención
A11: Movimiento de tierras y cimentación | B11: Retiro de sobrantes a botadero (80 % de lo excavado, con 25 % de esponjamiento) | C11: m³ | D11: 334.7 | E11: 28000 | F11: 38000 | G11: 55000 | H11: 0.2 | I11: 0.2 | J11: 0.2 | K11: =ROUND(D11*E11,0) | L11: =ROUND(D11*F11,0) | M11: =ROUND(D11*G11,0) | N11: =ROUND(K11*H11,0) | O11: =ROUND(L11*I11,0) | P11: =ROUND(M11*J11,0) | Q11: supuesto
A12: Movimiento de tierras y cimentación | B12: Relleno con material seleccionado compactado (mejoramiento de suelo expansivo) | C12: m³ | D12: 101.88 | E12: 80000 | F12: 115000 | G12: 150000 | H12: 0.25 | I12: 0.25 | J12: 0.25 | K12: =ROUND(D12*E12,0) | L12: =ROUND(D12*F12,0) | M12: =ROUND(D12*G12,0) | N12: =ROUND(K12*H12,0) | O12: =ROUND(L12*I12,0) | P12: =ROUND(M12*J12,0) | Q12: G10 | R12: reemplazo de 0,6 m de arcilla expansiva por material granular compactado
A13: Movimiento de tierras y cimentación | B13: Zapatas y vigas de cimentación, concreto 28 MPa con acero | C13: m³ | D13: 34.56 | E13: 1166200 | F13: 1414200 | G13: 1778800 | H13: 0.2023 | I13: 0.2348 | J13: 0.2683 | K13: =ROUND(D13*E13,0) | L13: =ROUND(D13*F13,0) | M13: =ROUND(D13*G13,0) | N13: =ROUND(K13*H13,0) | O13: =ROUND(L13*I13,0) | P13: =ROUND(M13*J13,0) | Q13: concreto G2 + vaciado L14 + 90 kg/m³ de acero instalado G3 + 4,4 m² de formaleta por m³ | R13: 26 zapatas 1,4×1,4×0,4 + 105 ml de vigas de cimentación 0,30×0,45
A14: Movimiento de tierras y cimentación | B14: Placa de contrapiso de 10 cm con malla | C14: m² | D14: 159.8 | E14: 78821 | F14: 95434 | G14: 119296 | H14: 0.2156 | I14: 0.2584 | J14: 0.311 | K14: =ROUND(D14*E14,0) | L14: =ROUND(D14*F14,0) | M14: =ROUND(D14*G14,0) | N14: =ROUND(K14*H14,0) | O14: =ROUND(L14*I14,0) | P14: =ROUND(M14*J14,0) | Q14: 0,105 m³ de concreto G1 + 3,2 kg de malla instalada (G3) + afinado | R14: placa de 10 cm con malla electrosoldada bajo toda la planta baja
A15: Estructura en concreto | B15: Columnas en concreto 28 MPa | C15: m³ | D15: 18.89 | E15: 1726200 | F15: 2121200 | G15: 2702800 | H15: 0.2575 | I15: 0.2838 | J15: 0.3092 | K15: =ROUND(D15*E15,0) | L15: =ROUND(D15*F15,0) | M15: =ROUND(D15*G15,0) | N15: =ROUND(K15*H15,0) | O15: =ROUND(L15*I15,0) | P15: =ROUND(M15*J15,0) | Q15: G2 + L14 + 160 kg/m³ de acero instalado (G3) + 11,4 m² de formaleta por m³ | R15: 26 columnas de 0,35×0,35 en PB, 20 en PA y 4 prolongadas en la doble altura
A16: Estructura en concreto | B16: Losa de entrepiso de 30 cm con vigas, voladizos y balcones | C16: m² | D16: 168.44 | E16: 300000 | F16: 390000 | G16: 520000 | H16: 0.25 | I16: 0.25 | J16: 0.25 | K16: =ROUND(D16*E16,0) | L16: =ROUND(D16*F16,0) | M16: =ROUND(D16*G16,0) | N16: =ROUND(K16*H16,0) | O16: =ROUND(L16*I16,0) | P16: =ROUND(M16*J16,0) | Q16: G7 | R16: losa sobre PB con alero sur de 1,2 m, losas de habitaciones 2 y 3, balcones norte en voladizo y techo de la ampliación
A17: Estructura en concreto | B17: Losa de cubierta con pórtico norte y aleros | C17: m² | D17: 148.88 | E17: 300000 | F17: 390000 | G17: 520000 | H17: 0.25 | I17: 0.25 | J17: 0.25 | K17: =ROUND(D17*E17,0) | L17: =ROUND(D17*F17,0) | M17: =ROUND(D17*G17,0) | N17: =ROUND(K17*H17,0) | O17: =ROUND(L17*I17,0) | P17: =ROUND(M17*J17,0) | Q17: G7 | R17: cubierta en L: 3,2×6,7 + 11,8×10,8 (con pórtico norte y alero sur)
A18: Estructura en concreto | B18: Escalera en U: tramo macizo, descanso y espina de concreto | C18: m³ | D18: 3.5 | E18: 1343000 | F18: 1639000 | G18: 2074000 | H18: 0.2276 | I18: 0.258 | J18: 0.2885 | K18: =ROUND(D18*E18,0) | L18: =ROUND(D18*F18,0) | M18: =ROUND(D18*G18,0) | N18: =ROUND(K18*H18,0) | O18: =ROUND(L18*I18,0) | P18: =ROUND(M18*J18,0) | Q18: 3,5 m³ con 110 kg/m³ de acero y 7 m² de formaleta por m³
A19: Estructura en concreto | B19: Muro de contención de 3 m bajo el borde infinito | C19: m³ | D19: 39.6 | E19: 1204600 | F19: 1472600 | G19: 1858400 | H19: 0.2146 | I19: 0.2438 | J19: 0.275 | K19: =ROUND(D19*E19,0) | L19: =ROUND(D19*F19,0) | M19: =ROUND(D19*G19,0) | N19: =ROUND(K19*H19,0) | O19: =ROUND(L19*I19,0) | P19: =ROUND(M19*J19,0) | Q19: 73 m² de muro de 30 cm + zapata de 24,4 × 1,8 × 0,4 m = 39,6 m³ de concreto G1 con 110 kg/m³ de acero
A20: Estructura en concreto | B20: Sobrecosto de concreto a la vista con formaleta de tabla | C20: m² | D20: 25.6 | E20: 70000 | F20: 120000 | G20: 200000 | H20: 0.5 | I20: 0.5 | J20: 0.5 | K20: =ROUND(D20*E20,0) | L20: =ROUND(D20*F20,0) | M20: =ROUND(D20*G20,0) | N20: =ROUND(K20*H20,0) | O20: =ROUND(L20*I20,0) | P20: =ROUND(M20*J20,0) | Q20: G13 | R20: cantos de losa vistos (52 ml × 0,3 m) + espina de la escalera
A21: Mampostería | B21: Muros en bloque con mortero, dovelas y vigas de amarre | C21: m² | D21: 342.78 | E21: 54981 | F21: 81833 | G21: 113725 | H21: 0.3056 | I21: 0.3148 | J21: 0.2955 | K21: =ROUND(D21*E21,0) | L21: =ROUND(D21*F21,0) | M21: =ROUND(D21*G21,0) | N21: =ROUND(K21*H21,0) | O21: =ROUND(L21*I21,0) | P21: =ROUND(M21*J21,0) | Q21: bloque G4 + 0,02 m³ de mortero (G5, G6) + mano de obra L10, +12 % por refuerzo y amarres | R21: muros exteriores PB 87 + interiores PB 90 + exteriores PA 52 + interiores PA 93 + antepechos de cubierta 21 (vanos descontados)
A22: Pañetes, estucos y pinturas | B22: Pañete de muros | C22: m² | D22: 673.56 | E22: 27000 | F22: 36500 | G22: 46000 | H22: 0.45 | I22: 0.45 | J22: 0.45 | K22: =ROUND(D22*E22,0) | L22: =ROUND(D22*F22,0) | M22: =ROUND(D22*G22,0) | N22: =ROUND(K22*H22,0) | O22: =ROUND(L22*I22,0) | P22: =ROUND(M22*J22,0) | Q22: F11 | R22: ambas caras de todos los muros + antepechos
A23: Pañetes, estucos y pinturas | B23: Estuco y pintura interior | C23: m² | D23: 422.78 | E23: 22000 | F23: 28000 | G23: 38000 | H23: 0.55 | I23: 0.55 | J23: 0.55 | K23: =ROUND(D23*E23,0) | L23: =ROUND(D23*F23,0) | M23: =ROUND(D23*G23,0) | N23: =ROUND(K23*H23,0) | O23: =ROUND(L23*I23,0) | P23: =ROUND(M23*J23,0) | Q23: F5 | R23: caras interiores menos 82 m² de muros de baño en microcemento
A24: Pañetes, estucos y pinturas | B24: Cielo raso en drywall con pintura | C24: m² | D24: 202 | E24: 58000 | F24: 80000 | G24: 110000 | H24: 0.45 | I24: 0.45 | J24: 0.45 | K24: =ROUND(D24*E24,0) | L24: =ROUND(D24*F24,0) | M24: =ROUND(D24*G24,0) | N24: =ROUND(K24*H24,0) | O24: =ROUND(L24*I24,0) | P24: =ROUND(M24*J24,0) | Q24: F7 | R24: cielos de PB (sin la zona de listones) y de PA incluido el vacío
A25: Pañetes, estucos y pinturas | B25: Pintura elastomérica de fachada y aleros | C25: m² | D25: 166.6 | E25: 32000 | F25: 45000 | G25: 65000 | H25: 0.55 | I25: 0.55 | J25: 0.55 | K25: =ROUND(D25*E25,0) | L25: =ROUND(D25*F25,0) | M25: =ROUND(D25*G25,0) | N25: =ROUND(K25*H25,0) | O25: =ROUND(L25*I25,0) | P25: =ROUND(M25*J25,0) | Q25: F6 | R25: muros de la caja superior + aletas del pórtico + antepechos y cantos + aleros
A26: Pisos y enchapes | B26: Alistado de pisos bajo porcelanato, madera y microcemento | C26: m² | D26: 200.75 | E26: 24000 | F26: 32000 | G26: 42000 | H26: 0.55 | I26: 0.55 | J26: 0.55 | K26: =ROUND(D26*E26,0) | L26: =ROUND(D26*F26,0) | M26: =ROUND(D26*G26,0) | N26: =ROUND(K26*H26,0) | O26: =ROUND(L26*I26,0) | P26: =ROUND(M26*J26,0) | Q26: supuesto
A27: Pisos y enchapes | B27: Porcelanato símil mármol 120×120 instalado (8 % de desperdicio) | C27: m² | D27: 89.65 | E27: 129600 | F27: 246400 | G27: 456600 | H27: 0.3086 | I27: 0.2435 | J27: 0.1862 | K27: =ROUND(D27*E27,0) | L27: =ROUND(D27*F27,0) | M27: =ROUND(D27*G27,0) | N27: =ROUND(K27*H27,0) | O27: =ROUND(L27*I27,0) | P27: =ROUND(M27*J27,0) | Q27: material F1 × 1,08 + instalación L13 + pegante y niveladores (supuesto) | R27: vestíbulo y oficina 9,2×3,1 + hall 8,14×2,5 + cocina, comedor y sala 10,74×3,8
A28: Pisos y enchapes | B28: Piso de roble de ingeniería instalado | C28: m² | D28: 66.1 | E28: 235000 | F28: 320000 | G28: 480000 | H28: 0.13 | I28: 0.13 | J28: 0.13 | K28: =ROUND(D28*E28,0) | L28: =ROUND(D28*F28,0) | M28: =ROUND(D28*G28,0) | N28: =ROUND(K28*H28,0) | O28: =ROUND(L28*I28,0) | P28: =ROUND(M28*J28,0) | Q28: F2 | R28: habitaciones 2 y 3, pasillo y galería, vestier y habitación principal
A29: Pisos y enchapes | B29: Microcemento en pisos y muros de baño | C29: m² | D29: 127.1 | E29: 125000 | F29: 175000 | G29: 270000 | H29: 0.5 | I29: 0.5 | J29: 0.5 | K29: =ROUND(D29*E29,0) | L29: =ROUND(D29*F29,0) | M29: =ROUND(D29*G29,0) | N29: =ROUND(K29*H29,0) | O29: =ROUND(L29*I29,0) | P29: =ROUND(M29*J29,0) | Q29: F3 | R29: pisos: baño social, servicio, suite de servicio y baños de PA (45 m²) + muros de los 4 baños (82 m²)
A30: Pisos y enchapes | B30: Concreto pulido y sellado en garaje | C30: m² | D30: 28.73 | E30: 45000 | F30: 65000 | G30: 90000 | H30: 0.5 | I30: 0.5 | J30: 0.5 | K30: =ROUND(D30*E30,0) | L30: =ROUND(D30*F30,0) | M30: =ROUND(D30*G30,0) | N30: =ROUND(K30*H30,0) | O30: =ROUND(L30*I30,0) | P30: =ROUND(M30*J30,0) | Q30: supuesto | R30: garaje
A31: Fachadas y madera | B31: Enchape de piedra coralina (fachadas, muro de contención y jardineras) | C31: m² | D31: 177.7 | E31: 215000 | F31: 270000 | G31: 370000 | H31: 0.3 | I31: 0.3 | J31: 0.3 | K31: =ROUND(D31*E31,0) | L31: =ROUND(D31*F31,0) | M31: =ROUND(D31*G31,0) | N31: =ROUND(K31*H31,0) | O31: =ROUND(L31*I31,0) | P31: =ROUND(M31*J31,0) | Q31: F4 | R31: muros exteriores de PB + cara del muro de contención + jardineras y muro bajo frontal
A32: Fachadas y madera | B32: Listones de madera: cielo de sala, celosías, pérgola y muro de TV | C32: m² | D32: 84.9 | E32: 230000 | F32: 340000 | G32: 520000 | H32: 0.35 | I32: 0.35 | J32: 0.35 | K32: =ROUND(D32*E32,0) | L32: =ROUND(D32*F32,0) | M32: =ROUND(D32*G32,0) | N32: =ROUND(K32*H32,0) | O32: =ROUND(L32*I32,0) | P32: =ROUND(M32*J32,0) | Q32: F10 | R32: cielo de sala y comedor + celosías oriente/occidente + pérgola + muro de TV
A33: Fachadas y madera | B33: Estructura metálica de pérgola y celosías | C33: global | D33: 1 | E33: 7000000 | F33: 9500000 | G33: 13000000 | H33: 0.4 | I33: 0.4 | J33: 0.4 | K33: =ROUND(D33*E33,0) | L33: =ROUND(D33*F33,0) | M33: =ROUND(D33*G33,0) | N33: =ROUND(K33*H33,0) | O33: =ROUND(L33*I33,0) | P33: =ROUND(M33*J33,0) | Q33: supuesto
A34: Cubiertas, impermeabilización y decks | B34: Impermeabilización de cubierta, terrazas y balcones | C34: m² | D34: 228.83 | E34: 60000 | F34: 110000 | G34: 165000 | H34: 0.35 | I34: 0.35 | J34: 0.35 | K34: =ROUND(D34*E34,0) | L34: =ROUND(D34*F34,0) | M34: =ROUND(D34*G34,0) | N34: =ROUND(K34*H34,0) | O34: =ROUND(L34*I34,0) | P34: =ROUND(M34*J34,0) | Q34: G12 | R34: cubierta + cubierta verde + terrazas y balcones sobre losa
A35: Cubiertas, impermeabilización y decks | B35: Cubierta verde extensiva | C35: m² | D35: 23.1 | E35: 170000 | F35: 240000 | G35: 350000 | H35: 0.3 | I35: 0.3 | J35: 0.3 | K35: =ROUND(D35*E35,0) | L35: =ROUND(D35*F35,0) | M35: =ROUND(D35*G35,0) | N35: =ROUND(K35*H35,0) | O35: =ROUND(L35*I35,0) | P35: =ROUND(M35*J35,0) | Q35: F12 | R35: franja sobre la sala y techo de la ampliación
A36: Cubiertas, impermeabilización y decks | B36: Gravilla de protección en cubierta | C36: m² | D36: 145 | E36: 12000 | F36: 18000 | G36: 26000 | H36: 0.4 | I36: 0.4 | J36: 0.4 | K36: =ROUND(D36*E36,0) | L36: =ROUND(D36*F36,0) | M36: =ROUND(D36*G36,0) | N36: =ROUND(K36*H36,0) | O36: =ROUND(L36*I36,0) | P36: =ROUND(M36*J36,0) | Q36: supuesto | R36: cubierta superior
A37: Cubiertas, impermeabilización y decks | B37: Deck de teca en terraza, balcones y patio de servicio | C37: m² | D37: 92.35 | E37: 350000 | F37: 480000 | G37: 680000 | H37: 0.3 | I37: 0.3 | J37: 0.3 | K37: =ROUND(D37*E37,0) | L37: =ROUND(D37*F37,0) | M37: =ROUND(D37*G37,0) | N37: =ROUND(K37*H37,0) | O37: =ROUND(L37*I37,0) | P37: =ROUND(M37*J37,0) | Q37: F8 | R37: terraza 11×3,2 + 2 balcones norte + balcón principal + terraza familiar + patio de servicio
A38: Instalaciones hidrosanitarias y gas | B38: Red hidrosanitaria completa (fría, caliente, desagües y aguas lluvias) | C38: m² | D38: 251.44 | E38: 150000 | F38: 210000 | G38: 290000 | H38: 0.45 | I38: 0.45 | J38: 0.45 | K38: =ROUND(D38*E38,0) | L38: =ROUND(D38*F38,0) | M38: =ROUND(D38*G38,0) | N38: =ROUND(K38*H38,0) | O38: =ROUND(L38*I38,0) | P38: =ROUND(M38*J38,0) | Q38: M3 | R38: PB 159.8 + PA 91.64
A39: Instalaciones hidrosanitarias y gas | B39: Red interna de gas natural | C39: global | D39: 1 | E39: 2500000 | F39: 3500000 | G39: 5000000 | H39: 0.5 | I39: 0.5 | J39: 0.5 | K39: =ROUND(D39*E39,0) | L39: =ROUND(D39*F39,0) | M39: =ROUND(D39*G39,0) | N39: =ROUND(K39*H39,0) | O39: =ROUND(L39*I39,0) | P39: =ROUND(M39*J39,0) | Q39: M4
A40: Instalaciones hidrosanitarias y gas | B40: Calentador de agua | C40: und | D40: 1 | E40: 2500000 | F40: 4000000 | G40: 7000000 | H40: 0.1 | I40: 0.1 | J40: 0.1 | K40: =ROUND(D40*E40,0) | L40: =ROUND(D40*F40,0) | M40: =ROUND(D40*G40,0) | N40: =ROUND(K40*H40,0) | O40: =ROUND(L40*I40,0) | P40: =ROUND(M40*J40,0) | Q40: W15
A41: Instalaciones eléctricas y datos | B41: Instalación eléctrica con tableros y certificación RETIE | C41: m² | D41: 251.44 | E41: 170000 | F41: 230000 | G41: 320000 | H41: 0.45 | I41: 0.45 | J41: 0.45 | K41: =ROUND(D41*E41,0) | L41: =ROUND(D41*F41,0) | M41: =ROUND(D41*G41,0) | N41: =ROUND(K41*H41,0) | O41: =ROUND(L41*I41,0) | P41: =ROUND(M41*J41,0) | Q41: M1 | R41: PB 159.8 + PA 91.64
A42: Instalaciones eléctricas y datos | B42: Iluminación LED interior y exterior | C42: m² | D42: 251.44 | E42: 60000 | F42: 95000 | G42: 150000 | H42: 0.2 | I42: 0.2 | J42: 0.2 | K42: =ROUND(D42*E42,0) | L42: =ROUND(D42*F42,0) | M42: =ROUND(D42*G42,0) | N42: =ROUND(K42*H42,0) | O42: =ROUND(L42*I42,0) | P42: =ROUND(M42*J42,0) | Q42: M2 | R42: PB 159.8 + PA 91.64
A43: Instalaciones eléctricas y datos | B43: Domótica básica de iluminación y escenas | C43: global | D43: 1 | E43: 6000000 | F43: 12000000 | G43: 25000000 | H43: 0.3 | I43: 0.3 | J43: 0.3 | K43: =ROUND(D43*E43,0) | L43: =ROUND(D43*F43,0) | M43: =ROUND(D43*G43,0) | N43: =ROUND(K43*H43,0) | O43: =ROUND(L43*I43,0) | P43: =ROUND(M43*J43,0) | Q43: M15
A44: Instalaciones eléctricas y datos | B44: Red de datos, CCTV y citofonía | C44: global | D44: 1 | E44: 4000000 | F44: 7000000 | G44: 12000000 | H44: 0.3 | I44: 0.3 | J44: 0.3 | K44: =ROUND(D44*E44,0) | L44: =ROUND(D44*F44,0) | M44: =ROUND(D44*G44,0) | N44: =ROUND(K44*H44,0) | O44: =ROUND(L44*I44,0) | P44: =ROUND(M44*J44,0) | Q44: M16
A45: Aire acondicionado | B45: Mini split inverter de 12.000 BTU instalado | C45: und | D45: 5 | E45: 2800000 | F45: 3600000 | G45: 4800000 | H45: 0.2 | I45: 0.2 | J45: 0.2 | K45: =ROUND(D45*E45,0) | L45: =ROUND(D45*F45,0) | M45: =ROUND(D45*G45,0) | N45: =ROUND(K45*H45,0) | O45: =ROUND(L45*I45,0) | P45: =ROUND(M45*J45,0) | Q45: M5 | R45: habitaciones 2, 3, principal, servicio y oficina
A46: Aire acondicionado | B46: Mini split inverter de 24.000 BTU instalado | C46: und | D46: 2 | E46: 4600000 | F46: 6000000 | G46: 8000000 | H46: 0.2 | I46: 0.2 | J46: 0.2 | K46: =ROUND(D46*E46,0) | L46: =ROUND(D46*F46,0) | M46: =ROUND(D46*G46,0) | N46: =ROUND(K46*H46,0) | O46: =ROUND(L46*I46,0) | P46: =ROUND(M46*J46,0) | Q46: M7 | R46: sala-comedor-cocina abierta (≈70 m² ligados a la doble altura)
A47: Carpintería en madera | B47: Cocina integral de alta gama con isla | C47: ml | D47: 6.3 | E47: 2200000 | F47: 3200000 | G47: 5000000 | H47: 0.25 | I47: 0.25 | J47: 0.25 | K47: =ROUND(D47*E47,0) | L47: =ROUND(D47*F47,0) | M47: =ROUND(D47*G47,0) | N47: =ROUND(K47*H47,0) | O47: =ROUND(L47*I47,0) | P47: =ROUND(M47*J47,0) | Q47: W6 | R47: mueble posterior 2,5 ml + torre de 1,2 ml + isla 2,6 ml
A48: Carpintería en madera | B48: Muebles de lavandería y despensa | C48: ml | D48: 4 | E48: 990000 | F48: 1440000 | G48: 2250000 | H48: 0.25 | I48: 0.25 | J48: 0.25 | K48: =ROUND(D48*E48,0) | L48: =ROUND(D48*F48,0) | M48: =ROUND(D48*G48,0) | N48: =ROUND(K48*H48,0) | O48: =ROUND(L48*I48,0) | P48: =ROUND(M48*J48,0) | Q48: 45 % del ml de cocina W6 (carpintería estándar) | R48: lavandería y despensa
A49: Carpintería en madera | B49: Closets y vestier | C49: ml | D49: 7.6 | E49: 1100000 | F49: 1600000 | G49: 2400000 | H49: 0.25 | I49: 0.25 | J49: 0.25 | K49: =ROUND(D49*E49,0) | L49: =ROUND(D49*F49,0) | M49: =ROUND(D49*G49,0) | N49: =ROUND(K49*H49,0) | O49: =ROUND(L49*I49,0) | P49: =ROUND(M49*J49,0) | Q49: W7 | R49: habitaciones 2, 3, servicio y vestier
A50: Carpintería en madera | B50: Puertas interiores con marco y herrajes | C50: und | D50: 14 | E50: 900000 | F50: 1300000 | G50: 2000000 | H50: 0.2 | I50: 0.2 | J50: 0.2 | K50: =ROUND(D50*E50,0) | L50: =ROUND(D50*F50,0) | M50: =ROUND(D50*G50,0) | N50: =ROUND(K50*H50,0) | O50: =ROUND(L50*I50,0) | P50: =ROUND(M50*J50,0) | Q50: W8 | R50: 8 en PB (oficina, baños, servicio, suite, patio) + 6 en PA
A51: Carpintería en madera | B51: Puerta principal pivotante en teca de 1,40 × 3,00 m | C51: und | D51: 1 | E51: 9000000 | F51: 14000000 | G51: 22000000 | H51: 0.15 | I51: 0.15 | J51: 0.15 | K51: =ROUND(D51*E51,0) | L51: =ROUND(D51*F51,0) | M51: =ROUND(D51*G51,0) | N51: =ROUND(K51*H51,0) | O51: =ROUND(L51*I51,0) | P51: =ROUND(M51*J51,0) | Q51: W4 | R51: 1,40 × 3,00 m en teca
A52: Carpintería en madera | B52: Muebles de baño flotantes | C52: und | D52: 4 | E52: 1400000 | F52: 2200000 | G52: 3500000 | H52: 0.15 | I52: 0.15 | J52: 0.15 | K52: =ROUND(D52*E52,0) | L52: =ROUND(D52*F52,0) | M52: =ROUND(D52*G52,0) | N52: =ROUND(K52*H52,0) | O52: =ROUND(L52*I52,0) | P52: =ROUND(M52*J52,0) | Q52: W14 | R52: vanity doble del principal, compartido, social y servicio
A53: Carpintería en madera | B53: Mesones en porcelánico o cuarzo | C53: ml | D53: 7.7 | E53: 900000 | F53: 1300000 | G53: 2000000 | H53: 0.2 | I53: 0.2 | J53: 0.2 | K53: =ROUND(D53*E53,0) | L53: =ROUND(D53*F53,0) | M53: =ROUND(D53*G53,0) | N53: =ROUND(K53*H53,0) | O53: =ROUND(L53*I53,0) | P53: =ROUND(M53*J53,0) | Q53: W16 | R53: cocina (isla y posterior) y lavandería
A54: Ventanería, vidrios y barandas | B54: Ventanería de aluminio negro con vidrio de control solar | C54: m² | D54: 111.05 | E54: 650000 | F54: 900000 | G54: 1300000 | H54: 0.2 | I54: 0.2 | J54: 0.2 | K54: =ROUND(D54*E54,0) | L54: =ROUND(D54*F54,0) | M54: =ROUND(D54*G54,0) | N54: =ROUND(K54*H54,0) | O54: =ROUND(L54*I54,0) | P54: =ROUND(M54*J54,0) | Q54: W1 | R54: ventanales corredizos de piso a techo y ventanas fijas de ambas plantas
A55: Ventanería, vidrios y barandas | B55: Muro cortina de doble altura en el vestíbulo | C55: m² | D55: 26.3 | E55: 900000 | F55: 1250000 | G55: 1800000 | H55: 0.2 | I55: 0.2 | J55: 0.2 | K55: =ROUND(D55*E55,0) | L55: =ROUND(D55*F55,0) | M55: =ROUND(D55*G55,0) | N55: =ROUND(K55*H55,0) | O55: =ROUND(L55*I55,0) | P55: =ROUND(M55*J55,0) | Q55: W2 | R55: doble altura del vestíbulo 5,0×6,1 menos la puerta pivotante
A56: Ventanería, vidrios y barandas | B56: Barandas de vidrio laminado templado | C56: ml | D56: 52.55 | E56: 900000 | F56: 1300000 | G56: 1900000 | H56: 0.2 | I56: 0.2 | J56: 0.2 | K56: =ROUND(D56*E56,0) | L56: =ROUND(D56*F56,0) | M56: =ROUND(D56*G56,0) | N56: =ROUND(K56*H56,0) | O56: =ROUND(L56*I56,0) | P56: =ROUND(M56*J56,0) | Q56: W3 | R56: galería, escalera, balcones, terraza familiar y deck de la piscina
... A64: Aparatos sanitarios y griferías | B64: Bañera exenta con grifería de piso | C64: und | D64: 1 | E64: 5500000 | F64: 8875000 | G64: 15500000 | H64: 0.08 | I64: 0.08 | J64: 0.08 | K64: =ROUND(D64*E64,0) | L64: =ROUND(D64*F64,0) | M64: =ROUND(D64*G64,0) | N64: =ROUND(K64*H64,0) | O64: =ROUND(L64*I64,0) | P64: =ROUND(M64*J64,0) | Q64: W12 + grifería de piso (2,5 × W10) | R64: exenta 1,70 m con grifería de piso
A65: Aparatos sanitarios y griferías | B65: Lavaplatos, lavadero y ducha de mascotas con griferías | C65: global | D65: 1 | E65: 2200000 | F65: 3600000 | G65: 6000000 | H65: 0.1 | I65: 0.1 | J65: 0.1 | K65: =ROUND(D65*E65,0) | L65: =ROUND(D65*F65,0) | M65: =ROUND(D65*G65,0) | N65: =ROUND(K65*H65,0) | O65: =ROUND(L65*I65,0) | P65: =ROUND(M65*J65,0) | Q65: supuesto
A66: Aparatos sanitarios y griferías | B66: Accesorios de baño | C66: baño | D66: 4 | E66: 450000 | F66: 800000 | G66: 1400000 | H66: 0.1 | I66: 0.1 | J66: 0.1 | K66: =ROUND(D66*E66,0) | L66: =ROUND(D66*F66,0) | M66: =ROUND(D66*G66,0) | N66: =ROUND(K66*H66,0) | O66: =ROUND(L66*I66,0) | P66: =ROUND(M66*J66,0) | Q66: supuesto
A67: Piscina y espejos de agua | B67: Piscina de borde infinito: vaso, impermeabilización, mosaico y canal de rebose | C67: m² | D67: 60 | E67: 2200000 | F67: 3000000 | G67: 4200000 | H67: 0.35 | I67: 0.35 | J67: 0.35 | K67: =ROUND(D67*E67,0) | L67: =ROUND(D67*F67,0) | M67: =ROUND(D67*G67,0) | N67: =ROUND(K67*H67,0) | O67: =ROUND(L67*I67,0) | P67: =ROUND(M67*J67,0) | Q67: P1 | R67: lámina de agua 15 × 4 m, profundidad 1,40 m, borde infinito al sur
A68: Piscina y espejos de agua | B68: Equipo de filtración y bombeo | C68: global | D68: 1 | E68: 12000000 | F68: 18000000 | G68: 28000000 | H68: 0.15 | I68: 0.15 | J68: 0.15 | K68: =ROUND(D68*E68,0) | L68: =ROUND(D68*F68,0) | M68: =ROUND(D68*G68,0) | N68: =ROUND(K68*H68,0) | O68: =ROUND(L68*I68,0) | P68: =ROUND(M68*J68,0) | Q68: P2
A69: Piscina y espejos de agua | B69: Iluminación LED subacuática | C69: global | D69: 1 | E69: 3000000 | F69: 5000000 | G69: 8000000 | H69: 0.15 | I69: 0.15 | J69: 0.15 | K69: =ROUND(D69*E69,0) | L69: =ROUND(D69*F69,0) | M69: =ROUND(D69*G69,0) | N69: =ROUND(K69*H69,0) | O69: =ROUND(L69*I69,0) | P69: =ROUND(M69*J69,0) | Q69: P3
A70: Piscina y espejos de agua | B70: Espejos de agua de la entrada | C70: m² | D70: 30.8 | E70: 900000 | F70: 1300000 | G70: 1900000 | H70: 0.35 | I70: 0.35 | J70: 0.35 | K70: =ROUND(D70*E70,0) | L70: =ROUND(D70*F70,0) | M70: =ROUND(D70*G70,0) | N70: =ROUND(K70*H70,0) | O70: =ROUND(L70*I70,0) | P70: =ROUND(M70*J70,0) | Q70: P5 | R70: dos espejos de agua de la entrada
A71: Energía solar | B71: Sistema fotovoltaico de 9,9 kWp conectado a red | C71: kWp | D71: 9.9 | E71: 3400000 | F71: 4000000 | G71: 4700000 | H71: 0.15 | I71: 0.15 | J71: 0.15 | K71: =ROUND(D71*E71,0) | L71: =ROUND(D71*F71,0) | M71: =ROUND(D71*G71,0) | N71: =ROUND(K71*H71,0) | O71: =ROUND(L71*I71,0) | P71: =ROUND(M71*J71,0) | Q71: M9 | R71: 18 paneles de 550 W
A72: Energía solar | B72: Batería de litio de respaldo | C72: kWh | D72: 10 | E72: 1600000 | F72: 2200000 | G72: 3000000 | H72: 0.05 | I72: 0.05 | J72: 0.05 | K72: =ROUND(D72*E72,0) | L72: =ROUND(D72*F72,0) | M72: =ROUND(D72*G72,0) | N72: =ROUND(K72*H72,0) | O72: =ROUND(L72*I72,0) | P72: =ROUND(M72*J72,0) | Q72: M10 | R72: respaldo de nevera, internet y luces
A73: Energía solar | B73: Mayor valor del inversor híbrido frente al de red | C73: und | D73: 1 | E73: 4500000 | F73: 6000000 | G73: 8000000 | H73: 0.05 | I73: 0.05 | J73: 0.05 | K73: =ROUND(D73*E73,0) | L73: =ROUND(D73*F73,0) | M73: =ROUND(D73*G73,0) | N73: =ROUND(K73*H73,0) | O73: =ROUND(L73*I73,0) | P73: =ROUND(M73*J73,0) | Q73: 50 % de M11
A74: Exteriores y paisajismo | B74: Travertino en el deck de la piscina | C74: m² | D74: 81.5 | E74: 210000 | F74: 285000 | G74: 420000 | H74: 0.3 | I74: 0.3 | J74: 0.3 | K74: =ROUND(D74*E74,0) | L74: =ROUND(D74*F74,0) | M74: =ROUND(D74*G74,0) | N74: =ROUND(K74*H74,0) | O74: =ROUND(L74*I74,0) | P74: =ROUND(M74*J74,0) | Q74: F9 | R74: deck norte, oeste y este de la piscina + remates del vaso
A75: Exteriores y paisajismo | B75: Losetas de concreto con junta verde en el acceso vehicular | C75: m² | D75: 38.5 | E75: 60000 | F75: 85000 | G75: 120000 | H75: 0.35 | I75: 0.35 | J75: 0.35 | K75: =ROUND(D75*E75,0) | L75: =ROUND(D75*F75,0) | M75: =ROUND(D75*G75,0) | N75: =ROUND(K75*H75,0) | O75: =ROUND(L75*I75,0) | P75: =ROUND(M75*J75,0) | Q75: P10 | R75: acceso vehicular 5,5 × 7 m
A76: Exteriores y paisajismo | B76: Sendero flotante en concreto con LED | C76: m² | D76: 10.5 | E76: 255650 | F76: 304600 | G76: 374000 | H76: 0.35 | I76: 0.35 | J76: 0.35 | K76: =ROUND(D76*E76,0) | L76: =ROUND(D76*F76,0) | M76: =ROUND(D76*G76,0) | N76: =ROUND(K76*H76,0) | O76: =ROUND(L76*I76,0) | P76: =ROUND(M76*J76,0) | Q76: 0,15 m³ de concreto G1 + 12 kg de acero instalado + formaleta + $60.000 de LED por m² (supuesto) | R76: sendero peatonal flotante sobre el espejo de agua
A77: Exteriores y paisajismo | B77: Grama | C77: m² | D77: 210 | E77: 20000 | F77: 28000 | G77: 40000 | H77: 0.4 | I77: 0.4 | J77: 0.4 | K77: =ROUND(D77*E77,0) | L77: =ROUND(D77*F77,0) | M77: =ROUND(D77*G77,0) | N77: =ROUND(K77*H77,0) | O77: =ROUND(L77*I77,0) | P77: =ROUND(M77*J77,0) | Q77: P6 | R77: lote 641,7 m² menos huella, decks, piscina, accesos, espejos de agua y jardineras
A78: Exteriores y paisajismo | B78: Palmas sembradas de 6 a 7 m | C78: und | D78: 8 | E78: 1200000 | F78: 2000000 | G78: 3500000 | H78: 0.3 | I78: 0.3 | J78: 0.3 | K78: =ROUND(D78*E78,0) | L78: =ROUND(D78*F78,0) | M78: =ROUND(D78*G78,0) | N78: =ROUND(K78*H78,0) | O78: =ROUND(L78*I78,0) | P78: =ROUND(M78*J78,0) | Q78: P7
A79: Exteriores y paisajismo | B79: Guayacanes sembrados | C79: und | D79: 2 | E79: 800000 | F79: 1500000 | G79: 2500000 | H79: 0.3 | I79: 0.3 | J79: 0.3 | K79: =ROUND(D79*E79,0) | L79: =ROUND(D79*F79,0) | M79: =ROUND(D79*G79,0) | N79: =ROUND(K79*H79,0) | O79: =ROUND(L79*I79,0) | P79: =ROUND(M79*J79,0) | Q79: P8 | R79: guayacanes amarillos dentro del lote
A80: Exteriores y paisajismo | B80: Setos de lindero | C80: ml | D80: 67 | E80: 35000 | F80: 55000 | G80: 80000 | H80: 0.3 | I80: 0.3 | J80: 0.3 | K80: =ROUND(D80*E80,0) | L80: =ROUND(D80*F80,0) | M80: =ROUND(D80*G80,0) | N80: =ROUND(K80*H80,0) | O80: =ROUND(L80*I80,0) | P80: =ROUND(M80*J80,0) | Q80: P9 | R80: linderos laterales y frente
A81: Exteriores y paisajismo | B81: Muro bajo frontal en coralina | C81: ml | D81: 16.7 | E81: 218241 | F81: 279825 | G81: 384176 | H81: 0.4 | I81: 0.4 | J81: 0.4 | K81: =ROUND(D81*E81,0) | L81: =ROUND(D81*F81,0) | M81: =ROUND(D81*G81,0) | N81: =ROUND(K81*H81,0) | O81: =ROUND(L81*I81,0) | P81: =ROUND(M81*J81,0) | Q81: dos caras de 0,45 m de coralina (F4) sobre núcleo de bloque | R81: muro bajo en coralina, h = 0,45 m
A82: Exteriores y paisajismo | B82: Patio de mascotas: casa de dos niveles, rampa y cerca | C82: global | D82: 1 | E82: 6500000 | F82: 9500000 | G82: 14000000 | H82: 0.45 | I82: 0.45 | J82: 0.45 | K82: =ROUND(D82*E82,0) | L82: =ROUND(D82*F82,0) | M82: =ROUND(D82*G82,0) | N82: =ROUND(K82*H82,0) | O82: =ROUND(L82*I82,0) | P82: =ROUND(M82*J82,0) | Q82: supuesto
A83: Exteriores y paisajismo | B83: Portones de los patios | C83: global | D83: 1 | E83: 1800000 | F83: 2800000 | G83: 4200000 | H83: 0.3 | I83: 0.3 | J83: 0.3 | K83: =ROUND(D83*E83,0) | L83: =ROUND(D83*F83,0) | M83: =ROUND(D83*G83,0) | N83: =ROUND(K83*H83,0) | O83: =ROUND(L83*I83,0) | P83: =ROUND(M83*J83,0) | Q83: supuesto
A84: Acometidas y aseo final | B84: Acometida y conexión eléctrica con Air-e | C84: global | D84: 1 | E84: 4000000 | F84: 6000000 | G84: 9000000 | H84: 0.4 | I84: 0.4 | J84: 0.4 | K84: =ROUND(D84*E84,0) | L84: =ROUND(D84*F84,0) | M84: =ROUND(D84*G84,0) | N84: =ROUND(K84*H84,0) | O84: =ROUND(L84*I84,0) | P84: =ROUND(M84*J84,0) | Q84: M13
A85: Acometidas y aseo final | B85: Acometida de acueducto y alcantarillado con Triple A | C85: global | D85: 1 | E85: 2500000 | F85: 4000000 | G85: 6000000 | H85: 0.4 | I85: 0.4 | J85: 0.4 | K85: =ROUND(D85*E85,0) | L85: =ROUND(D85*F85,0) | M85: =ROUND(D85*G85,0) | N85: =ROUND(K85*H85,0) | O85: =ROUND(L85*I85,0) | P85: =ROUND(M85*J85,0) | Q85: M14
A86: Acometidas y aseo final | B86: Aseo final y entrega | C86: m² | D86: 251.44 | E86: 6080 | F86: 7630 | G86: 10422 | H86: 0.9 | I86: 0.9 | J86: 0.9 | K86: =ROUND(D86*E86,0) | L86: =ROUND(D86*F86,0) | M86: =ROUND(D86*G86,0) | N86: =ROUND(K86*H86,0) | O86: =ROUND(L86*I86,0) | P86: =ROUND(M86*J86,0) | Q86: 0,03 jornales de cuadrilla por m² (L3, L4, L5) | R86: PB 159.8 + PA 91.64
B87: Costo directo total | K87: =SUM(K5:K86) | L87: =SUM(L5:L86) | M87: =SUM(M5:M86) | N87: =SUM(N5:N86) | O87: =SUM(O5:O86) | P87: =SUM(P5:P86)

Sheet Capítulos
A1: Capítulo | C1: Total bajo | D1: Total medio | E1: Total alto | F1: MO medio | G1: % MO medio | H1: % del costo directo (medio)
A2: Preliminares y obra provisional | C2: =SUMIF(Partidas!$A$5:$A$86,$A2,Partidas!K$5:K$86) | D2: =SUMIF(Partidas!$A$5:$A$86,$A2,Partidas!L$5:L$86) | E2: =SUMIF(Partidas!$A$5:$A$86,$A2,Partidas!M$5:M$86) | F2: =SUMIF(Partidas!$A$5:$A$86,$A2,Partidas!O$5:O$86) | G2: =F2/D2 | H2: =D2/Partidas!$L$87
A3: Movimiento de tierras y cimentación | C3: =SUMIF(Partidas!$A$5:$A$86,$A3,Partidas!K$5:K$86) | D3: =SUMIF(Partidas!$A$5:$A$86,$A3,Partidas!L$5:L$86) | E3: =SUMIF(Partidas!$A$5:$A$86,$A3,Partidas!M$5:M$86) | F3: =SUMIF(Partidas!$A$5:$A$86,$A3,Partidas!O$5:O$86) | G3: =F3/D3 | H3: =D3/Partidas!$L$87
A4: Estructura en concreto | C4: =SUMIF(Partidas!$A$5:$A$86,$A4,Partidas!K$5:K$86) | D4: =SUMIF(Partidas!$A$5:$A$86,$A4,Partidas!L$5:L$86) | E4: =SUMIF(Partidas!$A$5:$A$86,$A4,Partidas!M$5:M$86) | F4: =SUMIF(Partidas!$A$5:$A$86,$A4,Partidas!O$5:O$86) | G4: =F4/D4 | H4: =D4/Partidas!$L$87
A5: Mampostería | C5: =SUMIF(Partidas!$A$5:$A$86,$A5,Partidas!K$5:K$86) | D5: =SUMIF(Partidas!$A$5:$A$86,$A5,Partidas!L$5:L$86) | E5: =SUMIF(Partidas!$A$5:$A$86,$A5,Partidas!M$5:M$86) | F5: =SUMIF(Partidas!$A$5:$A$86,$A5,Partidas!O$5:O$86) | G5: =F5/D5 | H5: =D5/Partidas!$L$87
A6: Pañetes, estucos y pinturas | C6: =SUMIF(Partidas!$A$5:$A$86,$A6,Partidas!K$5:K$86) | D6: =SUMIF(Partidas!$A$5:$A$86,$A6,Partidas!L$5:L$86) | E6: =SUMIF(Partidas!$A$5:$A$86,$A6,Partidas!M$5:M$86) | F6: =SUMIF(Partidas!$A$5:$A$86,$A6,Partidas!O$5:O$86) | G6: =F6/D6 | H6: =D6/Partidas!$L$87
A7: Pisos y enchapes | C7: =SUMIF(Partidas!$A$5:$A$86,$A7,Partidas!K$5:K$86) | D7: =SUMIF(Partidas!$A$5:$A$86,$A7,Partidas!L$5:L$86) | E7: =SUMIF(Partidas!$A$5:$A$86,$A7,Partidas!M$5:M$86) | F7: =SUMIF(Partidas!$A$5:$A$86,$A7,Partidas!O$5:O$86) | G7: =F7/D7 | H7: =D7/Partidas!$L$87
A8: Fachadas y madera | C8: =SUMIF(Partidas!$A$5:$A$86,$A8,Partidas!K$5:K$86) | D8: =SUMIF(Partidas!$A$5:$A$86,$A8,Partidas!L$5:L$86) | E8: =SUMIF(Partidas!$A$5:$A$86,$A8,Partidas!M$5:M$86) | F8: =SUMIF(Partidas!$A$5:$A$86,$A8,Partidas!O$5:O$86) | G8: =F8/D8 | H8: =D8/Partidas!$L$87
A9: Cubiertas, impermeabilización y decks | C9: =SUMIF(Partidas!$A$5:$A$86,$A9,Partidas!K$5:K$86) | D9: =SUMIF(Partidas!$A$5:$A$86,$A9,Partidas!L$5:L$86) | E9: =SUMIF(Partidas!$A$5:$A$86,$A9,Partidas!M$5:M$86) | F9: =SUMIF(Partidas!$A$5:$A$86,$A9,Partidas!O$5:O$86) | G9: =F9/D9 | H9: =D9/Partidas!$L$87
A10: Instalaciones hidrosanitarias y gas | C10: =SUMIF(Partidas!$A$5:$A$86,$A10,Partidas!K$5:K$86) | D10: =SUMIF(Partidas!$A$5:$A$86,$A10,Partidas!L$5:L$86) | E10: =SUMIF(Partidas!$A$5:$A$86,$A10,Partidas!M$5:M$86) | F10: =SUMIF(Partidas!$A$5:$A$86,$A10,Partidas!O$5:O$86) | G10: =F10/D10 | H10: =D10/Partidas!$L$87
A11: Instalaciones eléctricas y datos | C11: =SUMIF(Partidas!$A$5:$A$86,$A11,Partidas!K$5:K$86) | D11: =SUMIF(Partidas!$A$5:$A$86,$A11,Partidas!L$5:L$86) | E11: =SUMIF(Partidas!$A$5:$A$86,$A11,Partidas!M$5:M$86) | F11: =SUMIF(Partidas!$A$5:$A$86,$A11,Partidas!O$5:O$86) | G11: =F11/D11 | H11: =D11/Partidas!$L$87
A12: Aire acondicionado | C12: =SUMIF(Partidas!$A$5:$A$86,$A12,Partidas!K$5:K$86) | D12: =SUMIF(Partidas!$A$5:$A$86,$A12,Partidas!L$5:L$86) | E12: =SUMIF(Partidas!$A$5:$A$86,$A12,Partidas!M$5:M$86) | F12: =SUMIF(Partidas!$A$5:$A$86,$A12,Partidas!O$5:O$86) | G12: =F12/D12 | H12: =D12/Partidas!$L$87
A13: Carpintería en madera | C13: =SUMIF(Partidas!$A$5:$A$86,$A13,Partidas!K$5:K$86) | D13: =SUMIF(Partidas!$A$5:$A$86,$A13,Partidas!L$5:L$86) | E13: =SUMIF(Partidas!$A$5:$A$86,$A13,Partidas!M$5:M$86) | F13: =SUMIF(Partidas!$A$5:$A$86,$A13,Partidas!O$5:O$86) | G13: =F13/D13 | H13: =D13/Partidas!$L$87
... A19: Acometidas y aseo final | C19: =SUMIF(Partidas!$A$5:$A$86,$A19,Partidas!K$5:K$86) | D19: =SUMIF(Partidas!$A$5:$A$86,$A19,Partidas!L$5:L$86) | E19: =SUMIF(Partidas!$A$5:$A$86,$A19,Partidas!M$5:M$86) | F19: =SUMIF(Partidas!$A$5:$A$86,$A19,Partidas!O$5:O$86) | G19: =F19/D19 | H19: =D19/Partidas!$L$87
A20: Total | C20: =SUM(C2:C19) | D20: =SUM(D2:D19) | E20: =SUM(E2:E19) | F20: =SUM(F2:F19)

Sheet Cronograma
A1: Cronograma de Casa Brisa · semana 0 = 2026-11-02 · 70 semanas
A2: Edite la semana de inicio o la duración (amarillo): las barras se redibujan. Las fechas no reprograman las sucesoras; para eso, cronograma.py.
J3: Nov 26 | O3: Dec 26 | S3: Jan 27 | W3: Feb 27 | AA3: Mar 27 | AF3: Apr 27 | AJ3: May 27 | AO3: Jun 27 | AS3: Jul 27 | AW3: Aug 27 | BB3: Sep 27 | BF3: Oct 27 | BJ3: Nov 27 | BO3: Dec 27 | BS3: Jan 28 | BX3: Feb 28
A4: ID | B4: Actividad | C4: Fase | D4: Inicio (sem) | E4: Duración (sem) | F4: Fecha inicio | G4: Fecha fin | H4: Holgura (sem) | I4: Ruta crítica | J4: 0 | K4: 1 | L4: 2 | M4: 3 | N4: 4 | O4: 5 | P4: 6 | Q4: 7 | R4: 8 | S4: 9 | T4: 10 | U4: 11 | V4: 12 | W4: 13 | X4: 14 | Y4: 15 | Z4: 16 | AA4: 17 | AB4: 18 | AC4: 19 | AD4: 20 | AE4: 21 | AF4: 22 | AG4: 23 | AH4: 24 | AI4: 25 | AJ4: 26 | AK4: 27 | AL4: 28 | AM4: 29 | AN4: 30 | AO4: 31 | AP4: 32 | AQ4: 33 | AR4: 34 | AS4: 35 | AT4: 36 | AU4: 37 | AV4: 38 | AW4: 39 | AX4: 40 | AY4: 41 | AZ4: 42 | BA4: 43 | BB4: 44 | BC4: 45 | BD4: 46 | BE4: 47 | BF4: 48 | BG4: 49 | BH4: 50 | BI4: 51 | BJ4: 52 | BK4: 53 | BL4: 54 | BM4: 55 | BN4: 56 | BO4: 57 | BP4: 58 | BQ4: 59 | BR4: 60 | BS4: 61 | BT4: 62 | BU4: 63 | BV4: 64 | BW4: 65 | BX4: 66 | BY4: 67 | BZ4: 68 | CA4: 69
A5: A1 | B5: Topografía y estudio de suelos | C5: Diseño y licencia | D5: 0 | E5: 3 | F5: =DATE(2026,11,2)+7*D5 | G5: =F5+7*E5-3 | H5: 0 | I5: sí
A6: A2 | B6: Diseños arquitectónico, estructural y técnicos | C6: Diseño y licencia | D6: 1 | E6: 10 | F6: =DATE(2026,11,2)+7*D6 | G6: =F6+7*E6-3 | H6: 0 | I6: sí
A7: A3 | B7: Licencia de construcción en curaduría | C7: Diseño y licencia | D7: 11 | E7: 12 | F7: =DATE(2026,11,2)+7*D7 | G7: =F7+7*E7-3 | H7: 0 | I7: sí
A8: A4 | B8: Contratación y pedidos de largo plazo | C8: Diseño y licencia | D8: 13 | E8: 6 | F8: =DATE(2026,11,2)+7*D8 | G8: =F8+7*E8-3 | H8: 32
A9: B1 | B9: Preliminares, cerramiento y replanteo | C9: Obra gris | D9: 23 | E9: 2 | F9: =DATE(2026,11,2)+7*D9 | G9: =F9+7*E9-3 | H9: 0 | I9: sí
A10: B2 | B10: Excavación y mejoramiento del suelo | C10: Obra gris | D10: 25 | E10: 3 | F10: =DATE(2026,11,2)+7*D10 | G10: =F10+7*E10-3 | H10: 0 | I10: sí
A11: B3 | B11: Cimentación y placa de contrapiso | C11: Obra gris | D11: 28 | E11: 4 | F11: =DATE(2026,11,2)+7*D11 | G11: =F11+7*E11-3 | H11: 0 | I11: sí
A12: B4 | B12: Columnas de PB y losa de entrepiso | C12: Obra gris | D12: 32 | E12: 6 | F12: =DATE(2026,11,2)+7*D12 | G12: =F12+7*E12-3 | H12: 0 | I12: sí
A13: B5 | B13: Columnas de PA y losa de cubierta | C13: Obra gris | D13: 38 | E13: 6 | F13: =DATE(2026,11,2)+7*D13 | G13: =F13+7*E13-3 | H13: 0 | I13: sí
A14: B6 | B14: Muro de contención y vaso de la piscina | C14: Obra gris | D14: 33 | E14: 7 | F14: =DATE(2026,11,2)+7*D14 | G14: =F14+7*E14-3 | H14: 24
A15: B7 | B15: Mampostería | C15: Obra gris | D15: 39 | E15: 7 | F15: =DATE(2026,11,2)+7*D15 | G15: =F15+7*E15-3 | H15: 1
A16: B8 | B16: Redes hidrosanitarias, gas y eléctricas (tubería) | C16: Obra gris | D16: 41 | E16: 9 | F16: =DATE(2026,11,2)+7*D16 | G16: =F16+7*E16-3 | H16: 20
A17: B9 | B17: Impermeabilización de cubierta y terrazas | C17: Obra gris | D17: 46 | E17: 2 | F17: =DATE(2026,11,2)+7*D17 | G17: =F17+7*E17-3 | H17: 22
A18: C1 | B18: Pañetes y cielos en drywall | C18: Acabados e instalaciones | D18: 44 | E18: 7 | F18: =DATE(2026,11,2)+7*D18 | G18: =F18+7*E18-3 | H18: 0 | I18: sí
A19: C2 | B19: Ventanería y muro cortina | C19: Acabados e instalaciones | D19: 47 | E19: 4 | F19: =DATE(2026,11,2)+7*D19 | G19: =F19+7*E19-3 | H19: 16
A20: C3 | B20: Fachada en coralina, concreto visto y listones | C20: Acabados e instalaciones | D20: 46 | E20: 6 | F20: =DATE(2026,11,2)+7*D20 | G20: =F20+7*E20-3 | H20: 18
A21: C4 | B21: Pisos y enchapes (porcelanato, microcemento) | C21: Acabados e instalaciones | D21: 51 | E21: 7 | F21: =DATE(2026,11,2)+7*D21 | G21: =F21+7*E21-3 | H21: 0 | I21: sí
A22: C5 | B22: Aire acondicionado y sistema solar | C22: Acabados e instalaciones | D22: 51 | E22: 3 | F22: =DATE(2026,11,2)+7*D22 | G22: =F22+7*E22-3 | H22: 16
A23: C6 | B23: Piso de roble y decks de teca | C23: Acabados e instalaciones | D23: 59 | E23: 3 | F23: =DATE(2026,11,2)+7*D23 | G23: =F23+7*E23-3 | H23: 0 | I23: sí
A24: C7 | B24: Carpintería: cocina, closets y puertas | C24: Acabados e instalaciones | D24: 60 | E24: 4 | F24: =DATE(2026,11,2)+7*D24 | G24: =F24+7*E24-3 | H24: 0 | I24: sí
A25: C8 | B25: Estuco, pintura y barandas de vidrio | C25: Acabados e instalaciones | D25: 62 | E25: 4 | F25: =DATE(2026,11,2)+7*D25 | G25: =F25+7*E25-3 | H25: 0 | I25: sí
A26: C9 | B26: Aparatos, griferías, iluminación y domótica | C26: Acabados e instalaciones | D26: 64 | E26: 3 | F26: =DATE(2026,11,2)+7*D26 | G26: =F26+7*E26-3 | H26: 0 | I26: sí
A27: D1 | B27: Acabados y equipos de la piscina | C27: Exteriores y entrega | D27: 53 | E27: 4 | F27: =DATE(2026,11,2)+7*D27 | G27: =F27+7*E27-3 | H27: 11
A28: D2 | B28: Exteriores, travertino y paisajismo | C28: Exteriores y entrega | D28: 63 | E28: 5 | F28: =DATE(2026,11,2)+7*D28 | G28: =F28+7*E28-3 | H28: 0 | I28: sí
A29: D3 | B29: Acometidas definitivas, RETIE y pruebas | C29: Exteriores y entrega | D29: 65 | E29: 3 | F29: =DATE(2026,11,2)+7*D29 | G29: =F29+7*E29-3 | H29: 0 | I29: sí
A30: D4 | B30: Aseo, revisión y entrega | C30: Exteriores y entrega | D30: 68 | E30: 2 | F30: =DATE(2026,11,2)+7*D30 | G30: =F30+7*E30-3 | H30: 0 | I30: sí
B32: Hitos
B33: Licencia aprobada | F33: 46486 | AF33: ◆
B34: Estructura terminada | F34: 46633 | BA34: ◆
B35: Casa cerrada (ventanería) | F35: 46682 | BH35: ◆
B36: Entrega | F36: 46815 | CA36: ◆

Sheet Flujo de caja
A1: Mes | B1: Bajo | C1: Medio | D1: Alto | E1: Acumulado medio | F1: % acumulado medio
A2: 2026-11 | B2: 9412832 | C2: 14570688 | D2: 22599488 | E2: =SUM($C$2:C2) | F2: =E2/SUM($C$2:$C$17)
A3: 2026-12 | B3: 9412832 | C3: 14570688 | D3: 22599488 | E3: =SUM($C$2:C3) | F3: =E3/SUM($C$2:$C$17)
A4: 2027-01 | B4: 4706416 | C4: 7285344 | D4: 11299744 | E4: =SUM($C$2:C4) | F4: =E4/SUM($C$2:$C$17)
A5: 2027-02 | B5: 0 | C5: 0 | D5: 0 | E5: =SUM($C$2:C5) | F5: =E5/SUM($C$2:$C$17)
A6: 2027-03 | B6: 0 | C6: 0 | D6: 0 | E6: =SUM($C$2:C6) | F6: =E6/SUM($C$2:$C$17)
A7: 2027-04 | B7: 98326156 | C7: 141806662 | D7: 208291852 | E7: =SUM($C$2:C7) | F7: =E7/SUM($C$2:$C$17)
A8: 2027-05 | B8: 87750479 | C8: 130915322 | D8: 196574738 | E8: =SUM($C$2:C8) | F8: =E8/SUM($C$2:$C$17)
A9: 2027-06 | B9: 113777546 | C9: 162719761 | D9: 237710393 | E9: =SUM($C$2:C9) | F9: =E9/SUM($C$2:$C$17)
A10: 2027-07 | B10: 150793514 | C10: 212832613 | D10: 307788259 | E10: =SUM($C$2:C10) | F10: =E10/SUM($C$2:$C$17)
A11: 2027-08 | B11: 144472096 | C11: 209848486 | D11: 308606600 | E11: =SUM($C$2:C11) | F11: =E11/SUM($C$2:$C$17)
A12: 2027-09 | B12: 142088446 | C12: 212424647 | D12: 318903225 | E12: =SUM($C$2:C12) | F12: =E12/SUM($C$2:$C$17)
A13: 2027-10 | B13: 206500627 | C13: 295232788 | D13: 433966809 | E13: =SUM($C$2:C13) | F13: =E13/SUM($C$2:$C$17)
... A17: 2028-02 | B17: 87202141 | C17: 137719452 | D17: 219669858 | E17: =SUM($C$2:C17) | F17: =E17/SUM($C$2:$C$17)
A18: Total | B18: =SUM(B2:B17) | C18: =SUM(C2:C17) | D18: =SUM(D2:D17)

Sheet Precios y fuentes
A1: Código | B1: Concepto | C1: Unidad | D1: Bajo | E1: Medio | F1: Alto | G1: Confianza | H1: Fuente principal | I1: Enlace | J1: Nota
A2: B1 | B2: Costo directo por m² de vivienda unifamiliar de acabados altos (estrato 5-6) en Barranquilla / Costa Caribe, sin lote | C2: COP/m² construido | D2: 2900000 | E2: 3500000 | F2: 4300000 | G2: media | H2: OneEstimate – Costos de construcción por m² en Colombia 2026 | I2: https://oneestimate.ai/es/blog/costos-construccion-por-m2-colombia-2026 | J2: No hay índice oficial de costo por m² por estrato; todas las cifras vienen de cotizadores, blogs y arquitectos, y se cruzaron entre sí. Varias incluyen AIU, así que el costo directo se obtuvo dividiendo por 1,25 (AIU típico de B4). El rango de OneEstimate para Barranquilla (3,4–5,5 M con AIU, tabla rotulada 2025) da 2,7–4,4 M de costo directo; actualizado con el ICOCED 2026 (alrededor de +6,6 %) queda en 2,9–4,7 M. El de Hubservice (3,5–5,8 M, no VIS Barranquilla) da 2,8–4,6 M. Mestre da 2,9–3,6 M para medio-alto. El IVA de los materiales va incluido porque para el constructor es costo no descontable; el IVA sobre la utilidad no va incluido. La fracción de mano de obra (~25 %) sale de lo que dice Camacol: la mano de obra pesa cerca del 25 % del costo directo, y en el ICOCED pesa 20,4 %. El valor cubre la edificación (estructura, mampostería, instalaciones, acabados), no piscina, paisajismo, solar ni obras exteriores; para esta casa sirve como contraste del presupuesto detallado.
A3: B2 | B3: Costo directo por m² de vivienda de lujo / premium, sin lote | C3: COP/m² construido | D3: 4000000 | E3: 4800000 | F3: 6000000 | G3: baja | H3: vivienda.com.co – Construcción en Colombia: precio por metro cuadrado en 2026 | I3: https://vivienda.com.co/precio-metro-cuadrado-construccion-colombia-2026/ | J3: No hay dato publicado específico de lujo en Barranquilla. Las fuentes son nacionales y comerciales: vivienda.com.co da 4,5–7,0 M para alta gama, Presucosto 4,0–6,0+ M con AIU incluido y Mestre más de 4,8 M para lujo. Como no todas aclaran si incluyen AIU, el costo directo se estimó en 4,0–6,0 M, con 4,8 M como valor típico; si a 4,5–7,0 se le quita un AIU del 20–25 %, queda en 3,6–5,8 M. Esta casa tiene muro cortina, teca, piscina de borde infinito, unos 140 m² de ventanería de piso a techo y concreto a la vista de formaleta de tabla, así que debería caer en este rango y no en B1. Con estas cifras, 251 m² × 4,8 M dan unos 1.205 M de costo directo de la edificación, antes de piscina, exteriores y AIU.
A4: B3 | B4: Variación anual del ICOCED (Colombia), la más reciente encontrada | C4: % anual | D4: 6.6 | E4: 6.6 | F4: 6.6 | G4: media | H4: Bancolombia Capital Inteligente – El nuevo mapa de los costos de construcción en Colombia | I4: https://www.bancolombia.com/empresas/capital-inteligente/actualidad-economica-sectorial/costos-construccion-colombia-mano-obra | J4: El dato anual más reciente encontrado es 6,6 % a junio de 2026 (total nacional, citado por Bancolombia el 25-sep-2026); no se pudo abrir el boletín de agosto de 2026. Serie: diciembre de 2025, 3,61 % anual (DANE); febrero de 2026, 6,31 % anual y 5,67 % en el año corrido (DANE). En 2026 el índice saltó por el alza del salario mínimo: el componente de mano de obra subió 13,9 % en el primer semestre. Para Barranquilla, el último dato publicado es 2,97 % (oct-2025 contra oct-2024), que la Secretaría de Hacienda usó para actualizar la tabla de delineación de 2026. Recomendación: para llevar precios de 2025 a 2026 usar cerca del 6,5 % en general y del 12–14 % en partidas que son casi solo mano de obra, no el 3 % del rango sugerido.
A5: B4 | B5: AIU total típico de contratista a precio global en vivienda | C5: % sobre costo directo | D5: 18 | E5: 25 | F5: 30 | G5: media | H5: OneEstimate – AIU en Colombia: qué es y cómo calcularlo (Guía 2026) | I5: https://oneestimate.ai/es/blog/aiu-colombia-guia-completa | J5: Desglose típico 2026: Administración 10–15 % (algunas guías de vivienda dan 12–18 %), Imprevistos 3–5 %, Utilidad 5–10 %. Ninguna norma fija el AIU de obra privada; las cifras son de práctica de mercado. vivienda.com.co, citando a DANE y Camacol, da 25–35 % adicional sobre el costo directo, sin IVA, terreno ni licencias. Para una casa unifamiliar a la medida, con obra pequeña y muchos acabados especiales, lo razonable es 22–28 %. El IVA del 19 % se suma aparte, sobre la U (ver B8).
A6: B5 | B6: Honorarios de administración delegada en vivienda | C6: % sobre costo directo real | D6: 8 | E6: 10 | F6: 15 | G6: media | H6: Corte Suprema de Justicia, Sala Laboral, SL1486-2024 (Rad. 98982) | I6: https://www.ambitojuridico.com/sites/default/files/2024-08/Sent-SL-14862024%2898982%29-24.pdf | J6: Referencia normativa: el reglamento de honorarios de arquitectura (Decreto 2090 de 1989) fija para la construcción por administración delegada el 10 % del costo base real (CBT-real) en las categorías A a G, y el 17 % en restauración (categoría H). Los gastos reembolsables se pagan aparte. La Corte Suprema (SL1486-2024) lo aplicó como 10 % a un caso de casas de categoría E. Una de las transcripciones del texto de Función Pública muestra '0.9%', lo que parece un error. En el mercado se negocian 8–15 %, según el tamaño y si el constructor asume personal de obra y equipos. Sobre los honorarios se cobra IVA del 19 %. En este modelo el propietario asume el riesgo de imprevistos y compra los materiales.
A7: B6 | B7: Tarifa del impuesto de delineación urbana en Barranquilla | C7: % del valor de la obra | D7: 3 | E7: 3 | F7: 3 | G7: alta | H7: Resolución DSH No. 002 de 2024 – Barranquilla | I7: https://barranquilla.gov.co/documento/resolucion-dsh-no-002-de-2024-18-de-diciembre-de-2024-delineacion-urbana/?version=1 | J7: Estatuto Tributario Distrital (Decreto 0119 de 2019, arts. 95–97): la tarifa es 3 % del valor final de la obra. Al expedirse la licencia se paga un anticipo del 2,5 % sobre el presupuesto de obra, que no puede ser inferior a los precios mínimos por m² de B7. Dentro de los 5 días siguientes al fin de la obra o al vencimiento de la licencia se presenta la declaración por el 100 % y se descuenta el anticipo. Para 251 m² con el mínimo de estrato 6: anticipo de unos $12,67 M. Si el valor real de la obra es de unos $1.300 M, el impuesto total es de unos $39 M.
A8: B7 | B8: Costo mínimo por m², uso residencial estrato 6, unifamiliar-bifamiliar (Res. DSH 002 de 2025, vigencia 2026) | C8: COP/m² | D8: 2019139 | E8: 2019139 | F8: 2019139 | G8: alta | H8: Gaceta Distrital 1252-2 – Resolución DSH No 002 de 2025 (vigencia 2026) | I8: https://barranquilla.gov.co/documento/gaceta-no-1252-2/?version=1 | J8: Tabla residencial de estrato 6 en la Res. DSH 002 de 2025 (26-dic-2025, Gaceta 1252-2): unifamiliar-bifamiliar $2.019.139; multifamiliar hasta 6 pisos $1.725.751; multifamiliar de más de 6 pisos $2.557.707. El orden de las columnas se confirmó con la Res. DSH 002 de 2023 (2024: 1.889.114 / 1.614.620 / 2.393.000) y la Res. DSH 002 de 2024 (2025: 1.960.900 / 1.675.975 / 2.483.934). Las cuentas cuadran exactas: 1.960.900 × 1,0297 = 2.019.139, y en estrato 1, 594.900 × 1,0297 = 612.569. WebFetch no pudo abrir el PDF por un error de DNS; los valores salen de extractos del índice de búsqueda de la gaceta oficial y de la copia de PwC. Es un valor mínimo fiscal, no un costo real de obra. Para 251 m²: base mínima $506.803.889 y anticipo del 2,5 % de $12.670.097.
A9: B8 | B9: IVA sobre la utilidad en contratos de obra con AIU | C9: % sobre la utilidad (o sobre los honorarios) | D9: 19 | E9: 19 | F9: 19 | G9: alta | H9: Gerencie – IVA en contratos de construcción de bienes inmuebles | I9: https://www.gerencie.com/iva-en-contratos-de-construccion-de-bienes-inmuebles.html | J9: Art. 3 del Decreto 1372 de 1992, compilado en el art. 1.3.1.7.9 del DUR 1625 de 2016: en la construcción de un inmueble, el IVA se causa sobre los honorarios o, si no se pactan honorarios, sobre la utilidad. Se aplica la tarifa general del 19 %. La utilidad pactada no puede ser menor que la comercial de contratos similares. El IVA pagado en materiales no es descontable para el constructor y por eso va dentro del costo directo. Efecto: con una U de 5–10 %, el IVA equivale a 0,95–1,9 % del costo directo. En administración delegada se aplica el 19 % sobre los honorarios. La DIAN aclara que la regla cubre obras inherentes a la construcción; lo que se puede retirar sin dañar el inmueble (por ejemplo equipos) se factura con IVA pleno.
A10: B9 | B10: Precio de venta por m² de casas nuevas de lujo en el norte de Barranquilla (Villa Campestre, Altos del Prado, Riomar), como contraste | C10: COP/m² construido (precio de oferta, incluye lote) | D10: 4500000 | E10: 6000000 | F10: 8000000 | G10: media | H10: Ukucela – Precio m² en Barranquilla 2026 | I10: https://ukucela.com/blog/precio-metro-cuadrado-barranquilla-2026 | J10: No hay índice oficial de casas nuevas de lujo; se usan precios de oferta de portales, que incluyen el lote y suelen estar 10–20 % por encima del precio de cierre. Algunos avisos, con el m² calculado: Villa Campestre, 251 m² por $1.100 M (≈ 4,4 M/m²); Villa Campestre, 310 m² por $2.500 M (≈ 8 M/m²); Villa Campestre, 620 m² por $3.300 M (≈ 5,3 M/m²). Ukucela ubica Riomar y Alto Prado en 4,5–6,5 M/m². Terraes da una mediana de 4,0 M/m² para toda la ciudad (P25–P75: 3,1–5,2; máximo ≈ 6,8). Los apartamentos nuevos de Riomar se anuncian en 9–12 M/m², pero esa cifra es la de un vendedor. Contraste: el costo directo de B2 más AIU (≈ 6,0 M/m²) ya iguala o supera el precio de venta típico de casas del sector, sin contar lote.
A11: L1 | B11: Salario mínimo mensual legal vigente 2026 (SMMLV) | C11: COP/mes | D11: 1750905 | E11: 1750905 | F11: 1750905 | G11: alta | H11: ConsultorSalud - Decretos 1469 y 1470 de 2025 | I11: https://consultorsalud.com/aumento-del-salario-minimo-en-colombia-2026/ | J11: Valor oficial: +23% sobre 2025. El Consejo de Estado suspendió provisionalmente el Decreto 1469/2025 el 12-feb-2026. El Decreto 0159 del 19-feb-2026 fijó transitoriamente el mismo valor, que sigue vigente hasta la sentencia de fondo. Es salario básico, sin prestaciones ni auxilio de transporte.
A12: L2 | B12: Auxilio de transporte 2026 | C12: COP/mes | D12: 249095 | E12: 249095 | F12: 249095 | G12: alta | H12: Colpensiones - Decreto 1470 de 2025 | I12: https://normativa.colpensiones.gov.co/compilacion/docs/decreto_1470_2025.htm | J12: Decreto 1470/2025: +24,5% sobre los $200.000 de 2025. Se paga a quien devenga hasta 2 SMMLV ($3.501.810), es decir, a ayudantes y oficiales. Entra en la base de cesantías y prima, no en la de vacaciones ni en la de aportes. SMMLV + auxilio = $2.000.000.
A13: L3 | B13: Jornal básico de oficial de construcción en Barranquilla (sin prestaciones) | C13: COP/día | D13: 76700 | E13: 90000 | F13: 118000 | G13: media | H13: Elempleo - Oficial de estructura y acabados (Atiempo), Barranquilla | I13: https://www.elempleo.com/co/ofertas-trabajo/oficial-de-obra-vivienda-barranquilla-1886774152 | J13: Jornal = pago al trabajador SIN prestaciones; L5 se aplica encima. Bajo: oferta formal real en Barranquilla de $2.300.000/mes entre 30 días. Medio: el mismo salario por día efectivamente trabajado (2,3 M / 26 días = $88.500 en semana de 6 días; esa oferta trabaja de lunes a viernes, lo que da unos $106.000 por día trabajado). Coincide con el pago diario informal típico. Alto: techo del rango de OneEstimate para Barranquilla y piso del de PresuCosto (este no aclara si incluye prestaciones). Los blogs comerciales dicen usar un SMMLV 2026 de $1.423.500, que en realidad es el de 2025, así que sus rangos probablemente subestiman 2026.
... A40: G13 | B40: Sobrecosto de concreto a la vista con formaleta de tabla (board-formed) frente a concreto con formaleta normal | C40: COP/m2 de superficie vista | D40: 70000 | E40: 120000 | F40: 200000 | G40: baja | H40: HerramientasPro - APU precios unitarios Colombia 2026 | I40: https://herramientaspro.com.co/ing-civil/apu-precios-unitarios/ | J40: No hay precio publicado del sobrecosto. Estimación propia. Formaleta normal reutilizada 3-5 veces ≈ 18.000-35.000/m². Formaleta de tabla rústica o cepillada con 1-2 usos, juntas selladas y alineación cuidadosa ≈ 60.000-100.000/m² (tabla ~50.000 según CYPE + armado). A eso se suman mezcla y vibrado cuidados, muestra de prueba, resanes de 20.000-65.000 (Findeter) e hidrofugante siloxano de ~15.000-25.000. Diferencia neta: bajo 70.000, medio 120.000, alto 200.000 (madera seleccionada, tabla de un solo uso, alto control de calidad). Aplica a la base de la fachada y a otros elementos vistos.
A41: F1 | B41: Porcelanato símil mármol gran formato 120x120 o 60x120 para piso (solo material) | C41: COP/m² | D41: 70000 | E41: 155000 | F41: 320000 | G41: media | H41: Homecenter Colombia: Corona Absolute 60x120, caja de 1,44 m² | I41: https://www.homecenter.com.co/homecenter-co/product/3047648/piso-porcelanato-absolute-60x120-cm-caja-144-m2-corona/3047648/
A42: F2 | B42: Piso de madera de ingeniería de roble, suministro e instalación | C42: COP/m² | D42: 235000 | E42: 320000 | F42: 480000 | G42: baja | H42: Homecenter Colombia: piso en madera natural, caja de 2,14 m² (especie no indicada) | I42: https://www.homecenter.com.co/homecenter-co/product/411972/piso-en-madera-caja-214-m2-natural/411972/
A43: F3 | B43: Microcemento en pisos y muros de baño, instalado (imprimación, malla, capas base y decorativas, sellador) | C43: COP/m² | D43: 125000 | E43: 175000 | F43: 270000 | G43: media | H43: CYPE, Generador de Precios Colombia: piso continuo de microcemento de 3 mm | I43: http://www.colombia.generadordeprecios.info/espacios_urbanos/Firmes_y_pisos_urbanos/Pisos_urbanos/Continuos_de_microcemento/Piso_continuo_de_microcemento.html
A44: F4 | B44: Enchape de fachada en piedra coralina, suministro e instalación | C44: COP/m² | D44: 215000 | E44: 270000 | F44: 370000 | G44: media | H44: ExpoAreniscas: piedra coralina | I44: https://www.expoareniscas.com/producto/piedra-coralina/
A45: F5 | B45: Estuco y pintura vinilo interior a tres manos, suministro e instalación | C45: COP/m² | D45: 22000 | E45: 28000 | F45: 38000 | G45: alta | H45: Gobernación de Boyacá, Anexo 1: APU 2025 (Res. 0050 del 5 de mayo de 2025) | I45: https://www.boyaca.gov.co/wp-content/uploads/2025/05/Anexo-1-Listado-de-APUS-resumido.pdf
A46: F6 | B46: Pintura elastomérica o impermeabilizante de fachada, suministro e instalación | C46: COP/m² | D46: 32000 | E46: 45000 | F46: 65000 | G46: media | H46: Homecenter Colombia: Koraza Impermeabilizante blanco, 1 galón (Pintuco) | I46: https://www.homecenter.com.co/homecenter-co/product/725622/pintura-1-galon-koraza-impermeabilizante-blanco-pintuco/725622/
A47: F7 | B47: Cielo raso en drywall con masilla y pintura, suministro e instalación | C47: COP/m² | D47: 58000 | E47: 80000 | F47: 110000 | G47: media | H47: Geztio: APU de cielo raso en drywall | I47: https://geztio.co/upa/co/cielo-raso-en-drywall
A48: F8 | B48: Deck exterior en madera de teca (o ipé/abarco) sobre losa, suministro e instalación | C48: COP/m² | D48: 350000 | E48: 480000 | F48: 680000 | G48: media | H48: Forandes: construcción de piso deck en madera de teca exterior, 16 m² | I48: https://forandes.com/producto/construccion-de-piso-deck-en-madera-teca-exterior/
A49: F9 | B49: Travertino o piedra natural antideslizante para el deck de la piscina, suministro e instalación | C49: COP/m² | D49: 210000 | E49: 285000 | F49: 420000 | G49: media | H49: MeUp Colombia: materiales para piscinas | I49: https://meup.co/categoria/piscinas
A50: F10 | B50: Celosía o cielo en listones de madera (teca o similar) con bastidor, suministro e instalación | C50: COP/m² | D50: 230000 | E50: 340000 | F50: 520000 | G50: baja | H50: Forandes: listón de deck en teca de 8 x 1,8 cm | I50: https://forandes.com/producto/liston-de-deck-en-teca-8-cm-x-1-8-cm-por-metro-cuadrado/
A51: F11 | B51: Pañete de muros (mortero 1:4 a 1:5, e = 1,5-2 cm), suministro e instalación | C51: COP/m² | D51: 27000 | E51: 36500 | F51: 46000 | G51: alta | H51: Gobernación de Boyacá, Anexo 1: APU 2025 | I51: https://www.boyaca.gov.co/wp-content/uploads/2025/05/Anexo-1-Listado-de-APUS-resumido.pdf
A52: F12 | B52: Cubierta verde extensiva (sedum o grama) sobre losa: membrana antirraíz, drenaje, geotextil, sustrato y vegetación, suministro e instalación | C52: COP/m² | D52: 170000 | E52: 240000 | F52: 350000 | G52: baja
A53: W1 | B53: Ventanería de aluminio negro con vidrio laminado de control solar, corrediza de piso a techo, s&i | C53: COP/m² | D53: 650000 | E53: 900000 | F53: 1300000 | G53: media | H53: Diseños y Estructuras JH, lista 2026 (Bogotá) | I53: https://disenosyestructurasjh.com/producto/ventana-corrediza/ | J53: Las series básicas instaladas en Bogotá arrancan en $270.000/m² y la termoacústica en $800.000/m² más IVA. Esta casa usa hojas grandes de piso a techo, perfil pesado anodizado negro y vidrio laminado de control solar, por eso el rango arranca por encima de la serie 80-25 con IVA. Barranquilla tiene fabricantes de primer nivel (Tecnoglass), lo que ayuda a conseguir el valor bajo.
A54: W2 | B54: Muro cortina / fachada flotante de doble altura | C54: COP/m² | D54: 900000 | E54: 1250000 | F54: 1800000 | G54: baja | H54: Estimación propia (sin precio publicado encontrado) | J54: Sin precio publicado. Se estima un 35-40 % por encima de W1 por la perfilería estructural de 6 m, el anclaje a losa y el vidrio laminado de mayor espesor.
A55: W3 | B55: Baranda de vidrio laminado templado 10+10 con perfil de piso | C55: COP/ml | D55: 900000 | E55: 1300000 | F55: 1900000 | G55: baja | H55: Estimación propia (sin precio publicado encontrado) | J55: Sin precio publicado de 2026. 1,05 m² de vidrio laminado templado por ml (≈$400-600 mil) + perfil de aluminio empotrado + pasamanos de acero + instalación.
A56: W4 | B56: Puerta principal pivotante en teca maciza 1,40 × 3,00 m con pivote | C56: COP/und | D56: 9000000 | E56: 14000000 | F56: 22000000 | G56: baja | H56: Estimación propia (sin precio publicado encontrado) | J56: Sin precio publicado. 4,2 m² de hoja maciza en teca con alma estructural, pivote de piso de alta carga y cerradura de seguridad.
A57: W5 | B57: Puerta de garaje seccional motorizada 2,35 × 2,40 | C57: COP/und | D57: 7000000 | E57: 9500000 | F57: 13000000 | G57: baja | H57: Estimación propia (sin precio publicado encontrado) | J57: Sin precio publicado de 2026. Panel aislado de aluminio con acabado madera, motor con control y sensores.
A58: W6 | B58: Cocina integral de alta gama (muebles, herrajes, sin mesón ni electrodomésticos) | C58: COP/ml | D58: 2200000 | E58: 3200000 | F58: 5000000 | G58: baja | H58: Roomix, renovar cocina 2026 | I58: https://roomix.ai/blog/cuanto-cuesta-renovar-cocina-2026 | J58: Las guías de 2026 dan $0,8-1,2 millones por ml en madera maciza sin mesón; una cocina con torres de piso a techo, enchape de nogal, herrajes de cierre suave e isla con caídas suma bajo y alto por ml lineal de planta, así que se toma 2,5-4 veces ese valor.
A59: W7 | B59: Closet o vestier de piso a techo en madera | C59: COP/ml | D59: 1100000 | E59: 1600000 | F59: 2400000 | G59: baja | H59: Estimación propia (sin precio publicado encontrado) | J59: Se toma 50 % del valor por ml de la cocina: misma carpintería, sin isla ni torres de electrodomésticos.
A60: W8 | B60: Puerta interior maciza con marco y herrajes, s&i | C60: COP/und | D60: 900000 | E60: 1300000 | F60: 2000000 | G60: baja | H60: Estimación propia (sin precio publicado encontrado) | J60: Sin precio publicado de 2026.
A61: W9 | B61: Sanitario suspendido con tanque empotrado | C61: COP/und | D61: 1600000 | E61: 2400000 | F61: 3600000 | G61: baja | H61: Estimación propia (sin precio publicado encontrado) | J61: Sin precio publicado. Incluye estructura empotrada y pulsador.
A62: W10 | B62: Grifería de lavamanos de alta gama | C62: COP/und | D62: 400000 | E62: 750000 | F62: 1400000 | G62: baja | H62: Estimación propia (sin precio publicado encontrado) | J62: Sin precio publicado.
A63: W11 | B63: Ducha completa con mezclador empotrado y regadera tipo lluvia | C63: COP/und | D63: 1200000 | E63: 2000000 | F63: 3500000 | G63: baja | H63: Estimación propia (sin precio publicado encontrado) | J63: Sin precio publicado.
A64: W12 | B64: Bañera exenta de 1,70 m en solid surface | C64: COP/und | D64: 4500000 | E64: 7000000 | F64: 12000000 | G64: baja | H64: Estimación propia (sin precio publicado encontrado) | J64: Sin precio publicado.
A65: W13 | B65: Lavamanos de sobreponer | C65: COP/und | D65: 350000 | E65: 600000 | F65: 1100000 | G65: baja | H65: Estimación propia (sin precio publicado encontrado) | J65: Sin precio publicado.
A66: W14 | B66: Mueble de baño flotante | C66: COP/und | D66: 1400000 | E66: 2200000 | F66: 3500000 | G66: baja | H66: Estimación propia (sin precio publicado encontrado) | J66: Promedio de un vanity doble y tres sencillos.
A67: W15 | B67: Calentador de agua de paso a gas de alta capacidad | C67: COP/und | D67: 2500000 | E67: 4000000 | F67: 7000000 | G67: baja | H67: Estimación propia (sin precio publicado encontrado) | J67: El valor alto corresponde a bomba de calor.
A68: W16 | B68: Mesón en porcelánico Calacatta de 12 mm | C68: COP/ml | D68: 900000 | E68: 1300000 | F68: 2000000 | G68: baja | H68: Estimación propia (sin precio publicado encontrado) | J68: Sin precio publicado; incluye corte, cantos y caídas en cascada de la isla.
A69: M1 | B69: Instalación eléctrica completa con tableros y RETIE | C69: COP/m² | D69: 170000 | E69: 230000 | F69: 320000 | G69: baja | H69: OneEstimate, APU instalaciones eléctricas | I69: https://oneestimate.ai/blog/apu-instalaciones-electricas-construccion | J69: Las guías ubican las eléctricas en 5-8 % del costo directo; con un costo directo de $4-4,5 millones/m² eso da $200-360 mil/m². Coherente con unas 160 salidas a ~$84.000 más tableros, acometida interna y puesta a tierra.
A70: M2 | B70: Iluminación LED interior y exterior (luminarias) | C70: COP/m² | D70: 60000 | E70: 95000 | F70: 150000 | G70: baja | H70: Estimación propia (sin precio publicado encontrado) | J70: Sin precio publicado.
A71: M3 | B71: Red hidrosanitaria completa (fría, caliente, desagües, aguas lluvias) | C71: COP/m² | D71: 150000 | E71: 210000 | F71: 290000 | G71: baja | H71: OneEstimate, APU instalaciones eléctricas | I71: https://oneestimate.ai/blog/apu-instalaciones-electricas-construccion | J71: Las guías ubican las hidrosanitarias en 6-10 % del costo directo; con 4 baños, cocina, lavandería y aguas lluvias de cubierta se toma la parte baja de ese rango.
A72: M4 | B72: Red interna de gas natural | C72: COP/global | D72: 2500000 | E72: 3500000 | F72: 5000000 | G72: baja | H72: Estimación propia (sin precio publicado encontrado) | J72: Sin precio publicado.
A73: M5 | B73: Mini split inverter de 12.000 BTU instalado | C73: COP/und | D73: 2800000 | E73: 3600000 | F73: 4800000 | G73: media | H73: Cuánto me cuesta, aire acondicionado (abr-2026) | I73: https://cuantomecuesta.com/co/aire-acondicionado/ | J73: Una calculadora colombiana de 2026 da unos $5 millones para equipos de 12.000-24.000 BTU instalados; para 12.000 BTU se toma la parte baja.
A74: M7 | B74: Mini split inverter de 24.000 BTU instalado | C74: COP/und | D74: 4600000 | E74: 6000000 | F74: 8000000 | G74: media | H74: Cuánto me cuesta, aire acondicionado (abr-2026) | I74: https://cuantomecuesta.com/co/aire-acondicionado/ | J74: Misma fuente que M5, parte alta del rango.
A75: M9 | B75: Sistema solar fotovoltaico conectado a red, instalado y legalizado | C75: COP/kWp | D75: 3400000 | E75: 4000000 | F75: 4700000 | G75: media | H75: OPS Colombia, guía 2026 | I75: https://www.opscolombia.com/blog/cuanto-cuesta-realmente-un-sistema-solar-en-colombia | J75: Varias guías de 2026 coinciden en $3,5-5 millones por kWp con RETIE y trámites ante el operador de red. La exclusión de IVA de la Ley 1715 ya se refleja en esos precios de mercado.
A76: M10 | B76: Batería de litio (LFP) para respaldo | C76: COP/kWh | D76: 1600000 | E76: 2200000 | F76: 3000000 | G76: baja | H76: Estimación propia (sin precio publicado encontrado) | J76: Sin precio publicado de 2026 en pesos.
A77: M11 | B77: Inversor híbrido de 10 kW | C77: COP/und | D77: 9000000 | E77: 12000000 | F77: 16000000 | G77: baja | H77: Estimación propia (sin precio publicado encontrado) | J77: Sin precio publicado; en el presupuesto solo entra el 50 % como mayor valor frente al inversor de red.
A78: M13 | B78: Acometida y conexión eléctrica con Air-e | C78: COP/global | D78: 4000000 | E78: 6000000 | F78: 9000000 | G78: baja | H78: Estimación propia (sin precio publicado encontrado) | J78: Sin precio publicado; incluye medidor bidireccional para el sistema solar.
A79: M14 | B79: Acometida de acueducto y alcantarillado con Triple A | C79: COP/global | D79: 2500000 | E79: 4000000 | F79: 6000000 | G79: baja | H79: Estimación propia (sin precio publicado encontrado) | J79: Sin precio publicado.
A80: M15 | B80: Domótica básica (iluminación y escenas) | C80: COP/global | D80: 6000000 | E80: 12000000 | F80: 25000000 | G80: baja | H80: Estimación propia (sin precio publicado encontrado) | J80: Sin precio publicado.
A81: M16 | B81: Red de datos, CCTV y citofonía | C81: COP/global | D81: 4000000 | E81: 7000000 | F81: 12000000 | G81: baja | H81: Estimación propia (sin precio publicado encontrado) | J81: Sin precio publicado.
A82: P1 | B82: Piscina de borde infinito en concreto: vaso, impermeabilización, mosaico vítreo y canal de rebose | C82: COP/m² | D82: 2200000 | E82: 3000000 | F82: 4200000 | G82: media | H82: Constructora J. Hernández, cotizador 2026 | I82: https://cotizar2026.constructorajhdez.com/ | J82: Las piscinas de concreto tradicionales cuestan $60-120 millones; una de 7 × 4 m, $50-80 millones, es decir $1,8-2,9 millones por m². El borde infinito agrega el canal de rebose, el tanque de compensación y un muro con tolerancia milimétrica, por eso el rango sube.
A83: P2 | B83: Equipo de filtración, bombeo y tanque de compensación | C83: COP/global | D83: 12000000 | E83: 18000000 | F83: 28000000 | G83: baja | H83: Estimación propia (sin precio publicado encontrado) | J83: Sin precio publicado.
A84: P3 | B84: Iluminación LED subacuática | C84: COP/global | D84: 3000000 | E84: 5000000 | F84: 8000000 | G84: baja | H84: Estimación propia (sin precio publicado encontrado) | J84: Sin precio publicado.
A85: P5 | B85: Espejo de agua de 20 cm con fondo de piedra y recirculación | C85: COP/m² | D85: 900000 | E85: 1300000 | F85: 1900000 | G85: baja | H85: Estimación propia (sin precio publicado encontrado) | J85: Sin precio publicado.
A86: P6 | B86: Grama bermuda instalada | C86: COP/m² | D86: 20000 | E86: 28000 | F86: 40000 | G86: baja | H86: Estimación propia (sin precio publicado encontrado) | J86: Sin precio publicado.
A87: P7 | B87: Palma de 6 a 7 m sembrada | C87: COP/und | D87: 1200000 | E87: 2000000 | F87: 3500000 | G87: baja | H87: Estimación propia (sin precio publicado encontrado) | J87: Sin precio publicado.
A88: P8 | B88: Guayacán grande sembrado | C88: COP/und | D88: 800000 | E88: 1500000 | F88: 2500000 | G88: baja | H88: Estimación propia (sin precio publicado encontrado) | J88: Sin precio publicado.
A89: P9 | B89: Seto de swinglea sembrado | C89: COP/ml | D89: 35000 | E89: 55000 | F89: 80000 | G89: baja | H89: Estimación propia (sin precio publicado encontrado) | J89: Sin precio publicado.
A90: P10 | B90: Losetas de concreto con junta verde sobre base granular | C90: COP/m² | D90: 60000 | E90: 85000 | F90: 120000 | G90: baja | H90: Estimación propia (sin precio publicado encontrado) | J90: Sin precio publicado.
A91: S1 | B91: Estudio de suelos con ensayos de expansión | C91: COP/global | D91: 3000000 | E91: 4500000 | F91: 7000000 | G91: baja | H91: Estimación propia (sin precio publicado encontrado) | J91: Sin precio publicado.
A92: S2 | B92: Diseño arquitectónico completo (anteproyecto, proyecto y planos de construcción) | C92: COP/m² | D92: 45000 | E92: 70000 | F92: 110000 | G92: baja | H92: Estimación propia (sin precio publicado encontrado) | J92: Sin tarifa publicada de 2026; el reglamento de honorarios (Decreto 2090 de 1989) cobra un porcentaje del costo de obra. $70.000/m² equivale a cerca del 1,5-2 % del costo directo.
A93: S3 | B93: Diseño estructural NSR-10 | C93: COP/m² | D93: 12000 | E93: 18000 | F93: 28000 | G93: baja | H93: Estimación propia (sin precio publicado encontrado) | J93: Sin precio publicado.
A94: S4 | B94: Diseños eléctrico RETIE, hidrosanitario y de gas | C94: COP/global | D94: 5000000 | E94: 8000000 | F94: 12000000 | G94: baja | H94: Estimación propia (sin precio publicado encontrado) | J94: Sin precio publicado.
A95: S5 | B95: Expensas de licencia de construcción en curaduría (251 m², estrato 6) | C95: COP/global | D95: 9000000 | E95: 9900000 | F95: 11000000 | G95: media | H95: Curaduría 1 de Medellín, fórmula de expensas | I95: https://curaduria1medellin.com/descargas/expensas.pdf | J95: Fórmula del Decreto 1077 de 2015: E = Cf·i·m + Cv·i·j·m, con Cf = 10,01 UVT ($524.264 en 2026), Cv ≈ $2.621.319, i = 2,5 (estrato 6), m ≈ 0,938 y j = 3,8/(0,12 + 800/251) = 1,15. Da $8,3 millones + IVA = $9,9 millones. El factor m de Barranquilla debe confirmarse con la curaduría.
A96: S6 | B96: Interventoría o supervisión técnica | C96: % del costo directo | D96: 3 | E96: 4 | F96: 6 | G96: baja | H96: Estimación propia (sin precio publicado encontrado) | J96: Sin tarifa publicada; práctica de mercado.
A97: S7 | B97: Levantamiento topográfico | C97: COP/global | D97: 1200000 | E97: 1800000 | F97: 2800000 | G97: baja | H97: Estimación propia (sin precio publicado encontrado) | J97: Sin precio publicado.
A98: S8 | B98: Pólizas de cumplimiento y responsabilidad civil | C98: % del contrato | D98: 0.6 | E98: 0.9 | F98: 1.3 | G98: baja | H98: Estimación propia (sin precio publicado encontrado) | J98: Sin tarifa publicada.
B100: Supuestos propios
B101: Cerramiento provisional con postes y polisombra: material por ml | D101: 18000 | E101: 26000 | F101: 38000
B102: Contenedor-bodega y baño portátil: alquiler mensual | D102: 1100000 | E102: 1500000 | F102: 2100000
B103: Agua y energía provisionales de obra: consumo mensual | D103: 550000 | E103: 850000 | F103: 1250000
B104: Cargue, transporte y disposición de sobrantes en botadero autorizado, por m³ suelto | D104: 28000 | E104: 38000 | F104: 55000
B105: Formaleta (alquiler + armado y desarme) por m² de contacto | D105: 28000 | E105: 38000 | F105: 52000
B106: Alistado de piso en mortero de nivelación (material + mano de obra) | D106: 24000 | E106: 32000 | F106: 42000
B107: Pegante flexible y sistema de nivelación para gran formato, por m² | D107: 14000 | E107: 19000 | F107: 26000
B108: Endurecedor, pulido y sellado de placa de garaje | D108: 45000 | E108: 65000 | F108: 90000
B109: Estructura metálica de pérgola y celosías (≈350 kg) suministrada, pintada e instalada | D109: 7000000 | E109: 9500000 | F109: 13000000
B110: Gravilla blanca de 3 cm sobre cubierta, por m² | D110: 12000 | E110: 18000 | F110: 26000
B111: Vidrio templado de 10 mm para ducha con herrajes, por m² | D111: 380000 | E111: 520000 | F111: 750000
B112: Espejo plata de 6 mm instalado, por m² | D112: 160000 | E112: 230000 | F112: 340000
... B116: Barandas y portones de los patios de servicio y mascotas | D116: 1800000 | E116: 2800000 | F116: 4200000
